{
  "bus": {
    "baud": 19200,
    "bits": 8,
    "endian": "L",
    "parity": "N",
    "stop": 2
  },
  "deviceClass": "refrigeration-controller",
  "family": "mpxone",
  "model": "MPXone Advanced",
  "profileId": "carel-modbus-mpxone-advanced-v1.0.0",
  "protocol": "modbus-rtu",
  "quirks": {},
  "regs": [
    {
      "a": 15,
      "fc": 1,
      "id": 1,
      "k": "/5",
      "l": "User interface unit of measure",
      "max": 5,
      "min": 5,
      "t": "bit",
      "w": 1
    },
    {
      "a": 60,
      "fc": 3,
      "id": 2,
      "k": "/AA",
      "l": "Assign channel for Modulating fan output",
      "max": 2,
      "min": 0,
      "t": "i16",
      "w": 1
    },
    {
      "a": 61,
      "fc": 3,
      "id": 3,
      "k": "/Ab",
      "l": "Assign channel for Modulating valve output",
      "max": 2,
      "min": 0,
      "t": "i16",
      "w": 1
    },
    {
      "a": 62,
      "fc": 3,
      "id": 4,
      "k": "/Ac",
      "l": "Assign channel for Modulating anti-sweat heater output",
      "max": 2,
      "min": 0,
      "t": "i16",
      "w": 1
    },
    {
      "a": 371,
      "fc": 3,
      "id": 5,
      "k": "/Ad",
      "l": "Assign channel for Modulating generic function",
      "max": 2,
      "min": 0,
      "t": "i16",
      "w": 1
    },
    {
      "a": 149,
      "fc": 3,
      "id": 6,
      "k": "/AE",
      "l": "Condenser Fan Analog Out Channel",
      "max": 2,
      "min": 0,
      "t": "i16",
      "w": 1
    },
    {
      "a": 167,
      "fc": 3,
      "id": 7,
      "k": "/AG",
      "l": "Compressor Analog Out Channel; 0 = not configured, 1 = Y1, 2 = Y2",
      "max": 2,
      "min": 0,
      "t": "i16",
      "w": 1
    },
    {
      "a": 15,
      "fc": 3,
      "id": 8,
      "k": "/cA",
      "l": "Air off temp. probe calibration",
      "max": 20,
      "min": -20,
      "s": 0.1,
      "t": "i16",
      "u": 1,
      "w": 1
    },
    {
      "a": 406,
      "fc": 3,
      "id": 9,
      "k": "/cAF",
      "l": "Auxiliary pressure probe (Aux) Calibration",
      "max": 20,
      "min": -20,
      "s": 0.1,
      "t": "i16",
      "w": 1
    },
    {
      "a": 407,
      "fc": 3,
      "id": 10,
      "k": "/cAG",
      "l": "Auxiliary pressure probe 2 (Aux2) Calibration",
      "max": 20,
      "min": -20,
      "s": 0.1,
      "t": "i16",
      "w": 1
    },
    {
      "a": 16,
      "fc": 3,
      "id": 11,
      "k": "/cb",
      "l": "Defrost temp. probe calibration",
      "max": 20,
      "min": -20,
      "s": 0.1,
      "t": "i16",
      "u": 1,
      "w": 1
    },
    {
      "a": 17,
      "fc": 3,
      "id": 12,
      "k": "/cc",
      "l": "Air on temp. probe calibration",
      "max": 20,
      "min": -20,
      "s": 0.1,
      "t": "i16",
      "u": 1,
      "w": 1
    },
    {
      "a": 18,
      "fc": 3,
      "id": 13,
      "k": "/cd",
      "l": "Suction temp. probe (tGs) calibration",
      "max": 20,
      "min": -20,
      "s": 0.1,
      "t": "i16",
      "u": 1,
      "w": 1
    },
    {
      "a": 19,
      "fc": 3,
      "id": 14,
      "k": "/cE",
      "l": "Evaporator pressure probe (PEu) calibration",
      "max": 20,
      "min": -20,
      "s": 0.1,
      "t": "i16",
      "w": 1
    },
    {
      "a": 20,
      "fc": 3,
      "id": 15,
      "k": "/cF",
      "l": "Defrost temp. probe 2 (Sd2)  calibration",
      "max": 20,
      "min": -20,
      "s": 0.1,
      "t": "i16",
      "u": 1,
      "w": 1
    },
    {
      "a": 21,
      "fc": 3,
      "id": 16,
      "k": "/cG",
      "l": "Auxiliary temp. probe (Aux) calibration",
      "max": 20,
      "min": -20,
      "s": 0.1,
      "t": "i16",
      "u": 1,
      "w": 1
    },
    {
      "a": 22,
      "fc": 3,
      "id": 17,
      "k": "/cH",
      "l": "Auxiliary temp. probe 2 (Aux2) calibration",
      "max": 20,
      "min": -20,
      "s": 0.1,
      "t": "i16",
      "u": 1,
      "w": 1
    },
    {
      "a": 23,
      "fc": 3,
      "id": 18,
      "k": "/cI",
      "l": "Ambient temp. probe (SA) calibration",
      "max": 20,
      "min": -20,
      "s": 0.1,
      "t": "i16",
      "u": 1,
      "w": 1
    },
    {
      "a": 24,
      "fc": 3,
      "id": 19,
      "k": "/cL",
      "l": "Ambient humidity probe (SU) calibration",
      "max": 20,
      "min": -20,
      "s": 0.1,
      "t": "i16",
      "w": 1
    },
    {
      "a": 145,
      "fc": 3,
      "id": 20,
      "k": "/cM",
      "l": "Glass temp. probe (Svt) calibration",
      "max": 20,
      "min": -20,
      "s": 0.1,
      "t": "i16",
      "u": 1,
      "w": 1
    },
    {
      "a": 25,
      "fc": 3,
      "id": 21,
      "k": "/cn",
      "l": "Dewpoint value (Sdp) calibration",
      "max": 20,
      "min": -20,
      "s": 0.1,
      "t": "i16",
      "u": 1,
      "w": 1
    },
    {
      "a": 26,
      "fc": 3,
      "id": 22,
      "k": "/co",
      "l": "Condenser temperature calibration",
      "max": 20,
      "min": -20,
      "s": 0.1,
      "t": "i16",
      "u": 1,
      "w": 1
    },
    {
      "a": 3,
      "fc": 3,
      "id": 23,
      "k": "/FA",
      "l": "Assign Air off temp. probe (Sm)",
      "max": 8,
      "min": -4,
      "t": "i16",
      "w": 1
    },
    {
      "a": 404,
      "fc": 3,
      "id": 24,
      "k": "/FAF",
      "l": "Assign Auxiliary Pressure probe (AuxP)",
      "max": 6,
      "min": -4,
      "t": "i16",
      "w": 1
    },
    {
      "a": 405,
      "fc": 3,
      "id": 25,
      "k": "/FAG",
      "l": "Assign Auxiliary2 Pressure probe (AuxP2)",
      "max": 6,
      "min": -4,
      "t": "i16",
      "w": 1
    },
    {
      "a": 4,
      "fc": 3,
      "id": 26,
      "k": "/Fb",
      "l": "Assign defrost temperature probe (Sd)",
      "max": 8,
      "min": -4,
      "t": "i16",
      "w": 1
    },
    {
      "a": 5,
      "fc": 3,
      "id": 27,
      "k": "/Fc",
      "l": "Assign intake temperature probe (Sr)",
      "max": 8,
      "min": -4,
      "t": "i16",
      "w": 1
    },
    {
      "a": 6,
      "fc": 3,
      "id": 28,
      "k": "/Fd",
      "l": "Assign superheated gas temperature probe (tGS)",
      "max": 8,
      "min": -4,
      "t": "i16",
      "w": 1
    },
    {
      "a": 7,
      "fc": 3,
      "id": 29,
      "k": "/FE",
      "l": "Assign saturated evaporation pressure/temperature probe (PEu/tEu)",
      "max": 8,
      "min": -4,
      "t": "i16",
      "w": 1
    },
    {
      "a": 8,
      "fc": 3,
      "id": 30,
      "k": "/FF",
      "l": "Assign defrost temperature probe 2 (Sd2)",
      "max": 8,
      "min": -4,
      "t": "i16",
      "w": 1
    },
    {
      "a": 9,
      "fc": 3,
      "id": 31,
      "k": "/FG",
      "l": "Assign auxiliary temperature probe 1 (Saux1)",
      "max": 8,
      "min": -4,
      "t": "i16",
      "w": 1
    },
    {
      "a": 10,
      "fc": 3,
      "id": 32,
      "k": "/FH",
      "l": "Assign auxiliary temperature probe 2 (Saux2)",
      "max": 8,
      "min": -4,
      "t": "i16",
      "w": 1
    },
    {
      "a": 11,
      "fc": 3,
      "id": 33,
      "k": "/FI",
      "l": "Assign ambient temperature probe (SA)",
      "max": 8,
      "min": -4,
      "t": "i16",
      "w": 1
    },
    {
      "a": 12,
      "fc": 3,
      "id": 34,
      "k": "/FL",
      "l": "Assign ambient humidity probe (SU)",
      "max": 8,
      "min": -4,
      "t": "i16",
      "w": 1
    },
    {
      "a": 13,
      "fc": 3,
      "id": 35,
      "k": "/FM",
      "l": "Assign glass temperature probe (Svt)",
      "max": 8,
      "min": -4,
      "t": "i16",
      "w": 1
    },
    {
      "a": 14,
      "fc": 3,
      "id": 36,
      "k": "/Fn",
      "l": "Assign dewpoint value (SdP) to a serial probe",
      "max": 0,
      "min": -4,
      "t": "i16",
      "w": 1
    },
    {
      "a": 375,
      "fc": 3,
      "id": 37,
      "k": "/Fo",
      "l": "Assign Condenser temp. probe (Sc)",
      "max": 8,
      "min": -4,
      "t": "i16",
      "w": 1
    },
    {
      "a": 0,
      "fc": 3,
      "id": 38,
      "k": "/P2",
      "l": "Type of probe, group 2 (S4, S5)",
      "max": 6,
      "min": 1,
      "t": "u16",
      "w": 1
    },
    {
      "a": 1,
      "fc": 3,
      "id": 39,
      "k": "/P3",
      "l": "Type of probe, group 3 (S6)",
      "max": 6,
      "min": 0,
      "t": "u16",
      "w": 1
    },
    {
      "a": 2,
      "fc": 3,
      "id": 40,
      "k": "/P4",
      "l": "Type of probe, group 4 (S7)",
      "max": 6,
      "min": 1,
      "t": "u16",
      "w": 1
    },
    {
      "a": 387,
      "fc": 3,
      "id": 41,
      "k": "/P6",
      "l": "Analog Output Channel Y1 Mode:",
      "max": 6,
      "min": 0,
      "t": "u16",
      "w": 1
    },
    {
      "a": 388,
      "fc": 3,
      "id": 42,
      "k": "/P7",
      "l": "Analog Output Channel Y2 Mode:",
      "max": 6,
      "min": 0,
      "t": "u16",
      "w": 1
    },
    {
      "a": 27,
      "fc": 1,
      "id": 43,
      "k": "A1",
      "l": "Alarm thresholds (AL, AH) for set point St",
      "max": 5,
      "min": 5,
      "t": "bit",
      "w": 1
    },
    {
      "a": 111,
      "fc": 3,
      "id": 44,
      "k": "AA",
      "l": "Assign probe for high (AH) and low (AL) temperature alarms",
      "max": 14,
      "min": 0,
      "t": "u16",
      "w": 1
    },
    {
      "a": 112,
      "fc": 3,
      "id": 45,
      "k": "AA2",
      "l": "Assign probe for high (AH2) and low (AL2) temperature alarms",
      "max": 14,
      "min": 0,
      "t": "u16",
      "w": 1
    },
    {
      "a": 118,
      "fc": 3,
      "id": 46,
      "k": "Ad",
      "l": "Delay time for high and low temp. alarms (AH, AL)",
      "max": 240,
      "min": 0,
      "t": "u16",
      "u": 23,
      "w": 1
    },
    {
      "a": 119,
      "fc": 3,
      "id": 47,
      "k": "Ad2",
      "l": "Delay time for high and low temp. alarms (AH2, AL2)",
      "max": 240,
      "min": 1,
      "t": "u16",
      "u": 23,
      "w": 1
    },
    {
      "a": 115,
      "fc": 3,
      "id": 48,
      "k": "AH",
      "l": "High temp. alarm threshold",
      "max": 50,
      "min": 0,
      "s": 0.1,
      "t": "u16",
      "w": 1
    },
    {
      "a": 117,
      "fc": 3,
      "id": 49,
      "k": "AH2",
      "l": "High temp. alarm 2 threshold",
      "max": 50,
      "min": 0,
      "s": 0.1,
      "t": "u16",
      "w": 1
    },
    {
      "a": 331,
      "fc": 3,
      "id": 50,
      "k": "AHA",
      "l": "Absolute high temperature alarm threshold",
      "max": 200,
      "min": -50,
      "s": 0.1,
      "t": "i16",
      "u": 1,
      "w": 1
    },
    {
      "a": 333,
      "fc": 3,
      "id": 51,
      "k": "AHA2",
      "l": "Absolute high temperature 2 alarm threshold",
      "max": 200,
      "min": -50,
      "s": 0.1,
      "t": "i16",
      "u": 1,
      "w": 1
    },
    {
      "a": 114,
      "fc": 3,
      "id": 52,
      "k": "AL",
      "l": "Low temp. alarm threshold",
      "max": 50,
      "min": 0,
      "s": 0.1,
      "t": "u16",
      "w": 1
    },
    {
      "a": 116,
      "fc": 3,
      "id": 53,
      "k": "AL2",
      "l": "Low temp. alarm 2 threshold",
      "max": 50,
      "min": 0,
      "s": 0.1,
      "t": "i16",
      "w": 1
    },
    {
      "a": 330,
      "fc": 3,
      "id": 54,
      "k": "ALA",
      "l": "Absolute low temperature alarm threshold",
      "max": 50,
      "min": -50,
      "s": 0.1,
      "t": "i16",
      "u": 1,
      "w": 1
    },
    {
      "a": 332,
      "fc": 3,
      "id": 55,
      "k": "ALA2",
      "l": "Absolute low temperature 2 alarm threshold",
      "max": 50,
      "min": -50,
      "s": 0.1,
      "t": "i16",
      "u": 1,
      "w": 1
    },
    {
      "a": 7,
      "fc": 4,
      "id": 56,
      "k": "Aux",
      "l": "Auxiliary temp. probe (Aux)",
      "max": 5,
      "min": 5,
      "s": 0.1,
      "t": "i16",
      "u": 1
    },
    {
      "a": 8,
      "fc": 4,
      "id": 57,
      "k": "Aux2",
      "l": "Auxiliary temp. probe 2 (Aux2)",
      "max": 5,
      "min": 5,
      "s": 0.1,
      "t": "i16",
      "u": 1
    },
    {
      "a": 81,
      "fc": 4,
      "id": 58,
      "k": "AuxP",
      "l": "Auxiliary pressure probe (AuxP)",
      "max": 5,
      "min": 5,
      "s": 0.1,
      "t": "i16"
    },
    {
      "a": 82,
      "fc": 4,
      "id": 59,
      "k": "AuxP2",
      "l": "Auxiliary pressure probe 2 (AuxP2)",
      "max": 5,
      "min": 5,
      "s": 0.1,
      "t": "i16"
    },
    {
      "a": 51,
      "fc": 2,
      "id": 60,
      "k": "CLEAN",
      "l": "Warning for Clean status",
      "max": 5,
      "min": 5,
      "t": "bit"
    },
    {
      "a": 154,
      "fc": 3,
      "id": 61,
      "k": "cP1",
      "l": "Initial valve position when control starts",
      "max": 100,
      "min": 0,
      "t": "u16",
      "u": 3,
      "w": 1
    },
    {
      "a": 80,
      "fc": 3,
      "id": 62,
      "k": "d0",
      "l": "Type of defrost",
      "max": 4,
      "min": 0,
      "t": "u16",
      "w": 1
    },
    {
      "a": 98,
      "fc": 3,
      "id": 63,
      "k": "d1S",
      "l": "Number of daily defrosts (td1)",
      "max": 14,
      "min": 0,
      "t": "u16",
      "w": 1
    },
    {
      "a": 99,
      "fc": 3,
      "id": 64,
      "k": "d2S",
      "l": "Number of daily defrosts (td2)",
      "max": 14,
      "min": 0,
      "t": "u16",
      "w": 1
    },
    {
      "a": 18,
      "fc": 2,
      "id": 65,
      "k": "dA",
      "l": "Delayed alarm from external contact",
      "max": 5,
      "min": 5,
      "t": "bit"
    },
    {
      "a": 90,
      "fc": 2,
      "id": 66,
      "k": "DA1",
      "l": "EVD mini/ice: probe S1 faulty or set alarm range exceeded",
      "max": 5,
      "min": 5,
      "t": "bit"
    },
    {
      "a": 91,
      "fc": 2,
      "id": 67,
      "k": "DA2",
      "l": "EVD mini/ice: probe S2 faulty or set alarm range exceeded",
      "max": 5,
      "min": 5,
      "t": "bit"
    },
    {
      "a": 383,
      "fc": 3,
      "id": 68,
      "k": "dEP",
      "l": "Anticipated defrost end threshold",
      "max": 99.9,
      "min": -99.9,
      "t": "f32",
      "w": 1
    },
    {
      "a": 384,
      "fc": 3,
      "id": 69,
      "k": "dET",
      "l": "Anticipated defrost end probe",
      "max": 14,
      "min": 0,
      "s": 0.1,
      "t": "u16",
      "u": 1,
      "w": 1
    },
    {
      "a": 59,
      "fc": 1,
      "id": 70,
      "k": "Dfr",
      "l": "Defrost command",
      "max": 5,
      "min": 5,
      "t": "u16",
      "w": 1
    },
    {
      "a": 17,
      "fc": 4,
      "id": 71,
      "k": "DfrStatus",
      "l": "Defrost steps status",
      "max": 5,
      "min": 0,
      "t": "u16"
    },
    {
      "a": 81,
      "fc": 3,
      "id": 72,
      "k": "dI",
      "l": "Max interval between consecutive defrost",
      "max": 240,
      "min": 0,
      "t": "u16",
      "u": 24,
      "w": 1
    },
    {
      "a": 31,
      "fc": 3,
      "id": 73,
      "k": "DIA",
      "l": "Assign immediate external alarm digital input",
      "max": 5,
      "min": -1,
      "t": "i16",
      "w": 1
    },
    {
      "a": 32,
      "fc": 3,
      "id": 74,
      "k": "DIb",
      "l": "Assign delayed external alarm digital input",
      "max": 5,
      "min": -1,
      "t": "i16",
      "w": 1
    },
    {
      "a": 33,
      "fc": 3,
      "id": 75,
      "k": "DIc",
      "l": "Assign enable defrost digital input",
      "max": 5,
      "min": -1,
      "t": "i16",
      "w": 1
    },
    {
      "a": 34,
      "fc": 3,
      "id": 76,
      "k": "DId",
      "l": "Assign start defrost digital input",
      "max": 5,
      "min": -1,
      "t": "i16",
      "w": 1
    },
    {
      "a": 35,
      "fc": 3,
      "id": 77,
      "k": "DIe",
      "l": "Assign door switch with comp. and fans OFF digital input",
      "max": 5,
      "min": -1,
      "t": "i16",
      "w": 1
    },
    {
      "a": 36,
      "fc": 3,
      "id": 78,
      "k": "DIf",
      "l": "Assign remote ON/OFF digital input",
      "max": 5,
      "min": -1,
      "t": "i16",
      "w": 1
    },
    {
      "a": 37,
      "fc": 3,
      "id": 79,
      "k": "DIg",
      "l": "Assign curtain switch digital input",
      "max": 5,
      "min": -1,
      "t": "i16",
      "w": 1
    },
    {
      "a": 38,
      "fc": 3,
      "id": 80,
      "k": "DIh",
      "l": "Assign start/stop continuous cycle digital input",
      "max": 5,
      "min": -1,
      "t": "i16",
      "w": 1
    },
    {
      "a": 39,
      "fc": 3,
      "id": 81,
      "k": "DIi",
      "l": "Assign input status monitoring digital input",
      "max": 5,
      "min": -1,
      "t": "i16",
      "w": 1
    },
    {
      "a": 40,
      "fc": 3,
      "id": 82,
      "k": "DIl",
      "l": "Assign retaining digital input digital input",
      "max": 5,
      "min": -1,
      "t": "i16",
      "w": 1
    },
    {
      "a": 41,
      "fc": 3,
      "id": 83,
      "k": "DIm",
      "l": "Assign Standby mode switch digital input",
      "max": 5,
      "min": -1,
      "t": "i16",
      "w": 1
    },
    {
      "a": 42,
      "fc": 3,
      "id": 84,
      "k": "DIn",
      "l": "Assign clean mode switch digital input",
      "max": 5,
      "min": -1,
      "t": "i16",
      "w": 1
    },
    {
      "a": 43,
      "fc": 3,
      "id": 85,
      "k": "DIo",
      "l": "Assign working parameters set change digital input",
      "max": 5,
      "min": -1,
      "t": "i16",
      "w": 1
    },
    {
      "a": 172,
      "fc": 3,
      "id": 86,
      "k": "dIt",
      "l": "Timer duration (timed input)",
      "max": 999,
      "min": 0,
      "t": "u16",
      "u": 23,
      "w": 1
    },
    {
      "a": 46,
      "fc": 3,
      "id": 87,
      "k": "DOA",
      "l": "Assign solenoid/comp. digital output",
      "max": 4,
      "min": 0,
      "t": "i16",
      "w": 1
    },
    {
      "a": 50,
      "fc": 3,
      "id": 88,
      "k": "DOe",
      "l": "Assign light digital output",
      "max": 4,
      "min": 0,
      "t": "i16",
      "w": 1
    },
    {
      "a": 52,
      "fc": 3,
      "id": 89,
      "k": "DOg",
      "l": "Assign defrost digital output",
      "max": 4,
      "min": 0,
      "t": "i16",
      "w": 1
    },
    {
      "a": 53,
      "fc": 3,
      "id": 90,
      "k": "DOh",
      "l": "Assign defrost 2 digital output",
      "max": 4,
      "min": 0,
      "t": "i16",
      "w": 1
    },
    {
      "a": 54,
      "fc": 3,
      "id": 91,
      "k": "DOi",
      "l": "Assign fans digital output",
      "max": 4,
      "min": 0,
      "t": "i16",
      "w": 1
    },
    {
      "a": 336,
      "fc": 3,
      "id": 92,
      "k": "DOk",
      "l": "Assign compressor 2 digital output",
      "max": 4,
      "min": 0,
      "t": "i16",
      "w": 1
    },
    {
      "a": 55,
      "fc": 3,
      "id": 93,
      "k": "DOl",
      "l": "Assign suction valve digital output",
      "max": 4,
      "min": 0,
      "t": "i16",
      "w": 1
    },
    {
      "a": 57,
      "fc": 3,
      "id": 94,
      "k": "DOn",
      "l": "Assign liquid valve digital output",
      "max": 4,
      "min": 0,
      "t": "i16",
      "w": 1
    },
    {
      "a": 58,
      "fc": 3,
      "id": 95,
      "k": "DOo",
      "l": "Assign timed digital output",
      "max": 4,
      "min": 0,
      "t": "i16",
      "w": 1
    },
    {
      "a": 59,
      "fc": 3,
      "id": 96,
      "k": "DOp",
      "l": "Assign drain heaters digital output",
      "max": 4,
      "min": 0,
      "t": "i16",
      "w": 1
    },
    {
      "a": 178,
      "fc": 3,
      "id": 97,
      "k": "DOQ",
      "l": "Assign Anti-sweat heaters digital output",
      "max": 4,
      "min": 0,
      "t": "i16",
      "w": 1
    },
    {
      "a": 19,
      "fc": 2,
      "id": 98,
      "k": "dor",
      "l": "Door open for too long",
      "max": 5,
      "min": 5,
      "t": "bit"
    },
    {
      "a": 84,
      "fc": 3,
      "id": 99,
      "k": "dP1",
      "l": "Max defrost duration",
      "max": 240,
      "min": 1,
      "t": "u16",
      "u": 23,
      "w": 1
    },
    {
      "a": 85,
      "fc": 3,
      "id": 100,
      "k": "dP2",
      "l": "Max secondary evap. defrost duration",
      "max": 240,
      "min": 1,
      "t": "u16",
      "u": 23,
      "w": 1
    },
    {
      "a": 25,
      "fc": 4,
      "id": 101,
      "k": "DT_Day",
      "l": "Day - Current value by internal RTC",
      "max": 31,
      "min": 1,
      "t": "u16"
    },
    {
      "a": 30,
      "fc": 4,
      "id": 102,
      "k": "DT_DoW",
      "l": "Day of week - Current value by internal RTC",
      "max": 7,
      "min": 0,
      "t": "u16"
    },
    {
      "a": 28,
      "fc": 4,
      "id": 103,
      "k": "DT_Hour",
      "l": "Hour - Current value by internal RTC",
      "max": 23,
      "min": 0,
      "t": "u16",
      "u": 24
    },
    {
      "a": 29,
      "fc": 4,
      "id": 104,
      "k": "DT_Min",
      "l": "Minutes - Current value by internal RTC",
      "max": 59,
      "min": 0,
      "t": "u16",
      "u": 23
    },
    {
      "a": 26,
      "fc": 4,
      "id": 105,
      "k": "DT_Month",
      "l": "Month - Current value by internal RTC",
      "max": 12,
      "min": 1,
      "t": "u16"
    },
    {
      "a": 27,
      "fc": 4,
      "id": 106,
      "k": "DT_year",
      "l": "Year - Current value by internal RTC",
      "max": 99,
      "min": 17,
      "t": "u16"
    },
    {
      "a": 82,
      "fc": 3,
      "id": 107,
      "k": "dt1",
      "l": "End defrost temp.(read by Sd)",
      "max": 50,
      "min": -50,
      "s": 0.1,
      "t": "i16",
      "u": 1,
      "w": 1
    },
    {
      "a": 83,
      "fc": 3,
      "id": 108,
      "k": "dt2",
      "l": "End defrost temp.(read by Sd2)",
      "max": 50,
      "min": -50,
      "s": 0.1,
      "t": "i16",
      "u": 1,
      "w": 1
    },
    {
      "a": 1,
      "fc": 2,
      "id": 109,
      "k": "E1",
      "l": "Probe S1 fault",
      "max": 5,
      "min": 5,
      "t": "bit"
    },
    {
      "a": 2,
      "fc": 2,
      "id": 110,
      "k": "E2",
      "l": "Probe S2 fault",
      "max": 5,
      "min": 5,
      "t": "bit"
    },
    {
      "a": 3,
      "fc": 2,
      "id": 111,
      "k": "E3",
      "l": "Probe S3 fault",
      "max": 5,
      "min": 5,
      "t": "bit"
    },
    {
      "a": 4,
      "fc": 2,
      "id": 112,
      "k": "E4",
      "l": "Probe S4 fault",
      "max": 5,
      "min": 5,
      "t": "bit"
    },
    {
      "a": 5,
      "fc": 2,
      "id": 113,
      "k": "E5",
      "l": "Probe S5 fault",
      "max": 5,
      "min": 5,
      "t": "bit"
    },
    {
      "a": 6,
      "fc": 2,
      "id": 114,
      "k": "E6",
      "l": "Probe S6 fault",
      "max": 5,
      "min": 5,
      "t": "bit"
    },
    {
      "a": 26,
      "fc": 2,
      "id": 115,
      "k": "Edc",
      "l": "Comm. error with stepper driver",
      "max": 5,
      "min": 5,
      "t": "bit"
    },
    {
      "a": 20,
      "fc": 2,
      "id": 116,
      "k": "Etc",
      "l": "Real time clock not updated",
      "max": 5,
      "min": 5,
      "t": "bit"
    },
    {
      "a": 173,
      "fc": 3,
      "id": 117,
      "k": "F10",
      "l": "Evap. fan forcing time at max speed",
      "max": 240,
      "min": 0,
      "t": "u16",
      "u": 22,
      "w": 1
    },
    {
      "a": 31,
      "fc": 1,
      "id": 118,
      "k": "F3",
      "l": "Evap. fans during defrost",
      "max": 5,
      "min": 5,
      "t": "bit",
      "w": 1
    },
    {
      "a": 129,
      "fc": 3,
      "id": 119,
      "k": "F6",
      "l": "Max evap fan speed",
      "max": 100,
      "s": 0.1,
      "t": "i16",
      "u": 3,
      "w": 1
    },
    {
      "a": 130,
      "fc": 3,
      "id": 120,
      "k": "F7",
      "l": "Min evap. fan speed",
      "min": 0,
      "s": 0.1,
      "t": "i16",
      "u": 3,
      "w": 1
    },
    {
      "a": 166,
      "fc": 3,
      "id": 121,
      "k": "F8",
      "l": "Evap. fan peak time",
      "max": 240,
      "min": 0,
      "t": "u16",
      "u": 23,
      "w": 1
    },
    {
      "a": 48,
      "fc": 4,
      "id": 122,
      "k": "FAA",
      "l": "Evap Fans Analog Output",
      "max": 5,
      "min": 5,
      "s": 0.1,
      "t": "i16"
    },
    {
      "a": 50,
      "fc": 4,
      "id": 123,
      "k": "FAb",
      "l": "Modulating valve Analog Output",
      "max": 5,
      "min": 5,
      "s": 0.1,
      "t": "i16"
    },
    {
      "a": 49,
      "fc": 4,
      "id": 124,
      "k": "FAc",
      "l": "Anti-sweat heater Analog Output",
      "max": 5,
      "min": 5,
      "s": 0.1,
      "t": "i16"
    },
    {
      "a": 51,
      "fc": 4,
      "id": 125,
      "k": "FAd",
      "l": "Modulating generic function output status",
      "max": 5,
      "min": 5,
      "s": 0.1,
      "t": "i16"
    },
    {
      "a": 16,
      "fc": 4,
      "id": 126,
      "k": "FAE",
      "l": "Condenser Fan Analog Output",
      "max": 5,
      "min": 5,
      "s": 0.1,
      "t": "u16",
      "u": 3
    },
    {
      "a": 52,
      "fc": 4,
      "id": 127,
      "k": "FAG",
      "l": "Compressor Analog Output",
      "max": 5,
      "min": 5,
      "s": 0.1,
      "t": "u16",
      "u": 3
    },
    {
      "a": 121,
      "fc": 2,
      "id": 128,
      "k": "FIV",
      "l": "Very low SH status",
      "max": 5,
      "min": 5,
      "t": "bit"
    },
    {
      "a": 66,
      "fc": 2,
      "id": 129,
      "k": "FOA",
      "l": "Solenoid digital output function status",
      "max": 5,
      "min": 5,
      "t": "bit"
    },
    {
      "a": 114,
      "fc": 2,
      "id": 130,
      "k": "FOAB",
      "l": "Condenser Fan Status digital output",
      "max": 5,
      "min": 5,
      "t": "bit"
    },
    {
      "a": 83,
      "fc": 2,
      "id": 131,
      "k": "FOb",
      "l": "Alarm digital output function status",
      "max": 5,
      "min": 5,
      "t": "bit"
    },
    {
      "a": 68,
      "fc": 2,
      "id": 132,
      "k": "FOc",
      "l": "Auxiliary digital output function status",
      "max": 5,
      "min": 5,
      "t": "bit"
    },
    {
      "a": 69,
      "fc": 2,
      "id": 133,
      "k": "FOd",
      "l": "Auxiliary serving Main digital output function status",
      "max": 5,
      "min": 5,
      "t": "bit"
    },
    {
      "a": 70,
      "fc": 2,
      "id": 134,
      "k": "FOE",
      "l": "Light digital output function status",
      "max": 5,
      "min": 5,
      "t": "bit"
    },
    {
      "a": 71,
      "fc": 2,
      "id": 135,
      "k": "FOF",
      "l": "Light serving Main digital output function status",
      "max": 5,
      "min": 5,
      "t": "bit"
    },
    {
      "a": 72,
      "fc": 2,
      "id": 136,
      "k": "FOG",
      "l": "Defrost digital output function status",
      "max": 5,
      "min": 5,
      "t": "bit"
    },
    {
      "a": 73,
      "fc": 2,
      "id": 137,
      "k": "FOH",
      "l": "Aux. evap. defrost digital output function status",
      "max": 5,
      "min": 5,
      "t": "bit"
    },
    {
      "a": 74,
      "fc": 2,
      "id": 138,
      "k": "FOI",
      "l": "Evap fans digital output function status",
      "max": 5,
      "min": 5,
      "t": "bit"
    },
    {
      "a": 98,
      "fc": 2,
      "id": 139,
      "k": "FOk",
      "l": "Compressor 2 output function status",
      "max": 5,
      "min": 5,
      "t": "bit"
    },
    {
      "a": 77,
      "fc": 2,
      "id": 140,
      "k": "FOn",
      "l": "Liquid Valve for pumpDown (before evap)",
      "max": 5,
      "min": 5,
      "t": "bit"
    },
    {
      "a": 78,
      "fc": 2,
      "id": 141,
      "k": "FOo",
      "l": "Timed digital output function status",
      "max": 5,
      "min": 5,
      "t": "bit"
    },
    {
      "a": 79,
      "fc": 2,
      "id": 142,
      "k": "FOP",
      "l": "Drain heater digital output function status",
      "max": 5,
      "min": 5,
      "t": "bit"
    },
    {
      "a": 85,
      "fc": 2,
      "id": 143,
      "k": "FOQ",
      "l": "Anti-sweat heater digital output function status",
      "max": 5,
      "min": 5,
      "t": "bit"
    },
    {
      "a": 221,
      "fc": 3,
      "id": 144,
      "k": "gas_c1",
      "l": "Reserved",
      "max": 5,
      "min": 5,
      "t": "i16",
      "w": 1
    },
    {
      "a": 228,
      "fc": 3,
      "id": 145,
      "k": "gas_c10",
      "l": "Reserved",
      "max": 5,
      "min": 5,
      "t": "i16",
      "w": 1
    },
    {
      "a": 231,
      "fc": 3,
      "id": 146,
      "k": "gas_c11",
      "l": "Reserved",
      "max": 5,
      "min": 5,
      "t": "i16",
      "w": 1
    },
    {
      "a": 230,
      "fc": 3,
      "id": 147,
      "k": "gas_c12",
      "l": "Reserved",
      "max": 5,
      "min": 5,
      "t": "i16",
      "w": 1
    },
    {
      "a": 220,
      "fc": 3,
      "id": 148,
      "k": "gas_c2",
      "l": "Reserved",
      "max": 5,
      "min": 5,
      "t": "i16",
      "w": 1
    },
    {
      "a": 223,
      "fc": 3,
      "id": 149,
      "k": "gas_c3",
      "l": "Reserved",
      "max": 5,
      "min": 5,
      "t": "i16",
      "w": 1
    },
    {
      "a": 222,
      "fc": 3,
      "id": 150,
      "k": "gas_c4",
      "l": "Reserved",
      "max": 5,
      "min": 5,
      "t": "i16",
      "w": 1
    },
    {
      "a": 225,
      "fc": 3,
      "id": 151,
      "k": "gas_c5",
      "l": "Reserved",
      "max": 5,
      "min": 5,
      "t": "i16",
      "w": 1
    },
    {
      "a": 224,
      "fc": 3,
      "id": 152,
      "k": "gas_c6",
      "l": "Reserved",
      "max": 5,
      "min": 5,
      "t": "i16",
      "w": 1
    },
    {
      "a": 227,
      "fc": 3,
      "id": 153,
      "k": "gas_c7",
      "l": "Reserved",
      "max": 5,
      "min": 5,
      "t": "i16",
      "w": 1
    },
    {
      "a": 226,
      "fc": 3,
      "id": 154,
      "k": "gas_c8",
      "l": "Reserved",
      "max": 5,
      "min": 5,
      "t": "i16",
      "w": 1
    },
    {
      "a": 229,
      "fc": 3,
      "id": 155,
      "k": "gas_c9",
      "l": "Reserved",
      "max": 5,
      "min": 5,
      "t": "i16",
      "w": 1
    },
    {
      "a": 232,
      "fc": 3,
      "id": 156,
      "k": "gas_CRC",
      "l": "Reserved",
      "max": 5,
      "min": 5,
      "t": "i16",
      "w": 1
    },
    {
      "a": 219,
      "fc": 3,
      "id": 157,
      "k": "gas_ID",
      "l": "Reserved",
      "max": 999,
      "min": -999,
      "t": "f32",
      "w": 1
    },
    {
      "a": 306,
      "fc": 3,
      "id": 158,
      "k": "GFA_Hth",
      "l": "Generic function alarm: high threshold",
      "max": 200,
      "min": -50,
      "s": 0.1,
      "t": "i16",
      "u": 1,
      "w": 1
    },
    {
      "a": 307,
      "fc": 3,
      "id": 159,
      "k": "GFA_Lth",
      "l": "Generic function alarm: low threshold",
      "max": 200,
      "min": -50,
      "s": 0.1,
      "t": "i16",
      "u": 1,
      "w": 1
    },
    {
      "a": 299,
      "fc": 3,
      "id": 160,
      "k": "GFM_Kp",
      "l": "Generic function modulating: proportional gain",
      "max": 100,
      "min": 0,
      "s": 0.1,
      "t": "u16",
      "w": 1
    },
    {
      "a": 297,
      "fc": 3,
      "id": 161,
      "k": "GFM_Max",
      "l": "Generic function modulating: maximum output value",
      "max": 100,
      "min": 0,
      "s": 0.1,
      "t": "u16",
      "w": 1
    },
    {
      "a": 298,
      "fc": 3,
      "id": 162,
      "k": "GFM_Min",
      "l": "Generic function modulating: minimum output value",
      "max": 100,
      "min": 0,
      "s": 0.1,
      "t": "u16",
      "w": 1
    },
    {
      "a": 293,
      "fc": 3,
      "id": 163,
      "k": "GFM_S",
      "l": "Generic function modulating: set point",
      "max": 200,
      "min": -50,
      "s": 0.1,
      "t": "u16",
      "u": 1,
      "w": 1
    },
    {
      "a": 81,
      "fc": 1,
      "id": 164,
      "k": "GFM_T",
      "l": "Generic function modulating: type",
      "max": 1,
      "min": 0,
      "t": "bit",
      "w": 1
    },
    {
      "a": 301,
      "fc": 3,
      "id": 165,
      "k": "GFM_Td",
      "l": "Generic function modulating: derivative time",
      "max": 100,
      "min": 0,
      "t": "u16",
      "w": 1
    },
    {
      "a": 300,
      "fc": 3,
      "id": 166,
      "k": "GFM_Ti",
      "l": "Generic function modulating: integral time",
      "max": 900,
      "min": 0,
      "t": "u16",
      "w": 1
    },
    {
      "a": 290,
      "fc": 3,
      "id": 167,
      "k": "GFS_1",
      "l": "Generic function On/Off: regulation probe 1",
      "max": 20,
      "min": 0,
      "t": "u16",
      "w": 1
    },
    {
      "a": 292,
      "fc": 3,
      "id": 168,
      "k": "GFS_E",
      "l": "Generic function On/Off: enable",
      "max": 10,
      "min": 0,
      "t": "u16",
      "w": 1
    },
    {
      "a": 288,
      "fc": 3,
      "id": 169,
      "k": "GFS_S",
      "l": "Generic function On/Off: set point",
      "max": 200,
      "min": -50,
      "s": 0.1,
      "t": "i16",
      "u": 1,
      "w": 1
    },
    {
      "a": 94,
      "fc": 2,
      "id": 170,
      "k": "GHI",
      "l": "Generic alarm 1 - High",
      "max": 5,
      "min": 5,
      "t": "bit"
    },
    {
      "a": 95,
      "fc": 2,
      "id": 171,
      "k": "GLO",
      "l": "Generic alarm 1 - Low",
      "max": 5,
      "min": 5,
      "t": "bit"
    },
    {
      "a": 162,
      "fc": 3,
      "id": 172,
      "k": "H0",
      "l": "BMS network address",
      "max": 247,
      "min": 1,
      "t": "u16"
    },
    {
      "a": 163,
      "fc": 3,
      "id": 173,
      "k": "H1",
      "l": "BMS config.(stop bit and parity)",
      "max": 5,
      "min": 0,
      "t": "u16"
    },
    {
      "a": 174,
      "fc": 3,
      "id": 174,
      "k": "H14",
      "l": "Time light stays on after closing the door",
      "max": 240,
      "min": 0,
      "t": "u16",
      "u": 23,
      "w": 1
    },
    {
      "a": 164,
      "fc": 3,
      "id": 175,
      "k": "H2",
      "l": "BMS baudrate (bit/s)",
      "max": 8,
      "min": 0,
      "t": "u16"
    },
    {
      "a": 38,
      "fc": 1,
      "id": 176,
      "k": "H3",
      "l": "BMS protocol",
      "max": 5,
      "min": 5,
      "t": "bit"
    },
    {
      "a": 78,
      "fc": 1,
      "id": 177,
      "k": "H6",
      "l": "Enable 7-seg UI keyboard",
      "max": 5,
      "min": 5,
      "t": "bit",
      "w": 1
    },
    {
      "a": 40,
      "fc": 1,
      "id": 178,
      "k": "H8",
      "l": "Terminal buzzer",
      "max": 5,
      "min": 5,
      "t": "bit",
      "w": 1
    },
    {
      "a": 20,
      "fc": 4,
      "id": 179,
      "k": "Han",
      "l": "HACCP number of HA alarm type recorded",
      "max": 255,
      "min": 0,
      "t": "u16"
    },
    {
      "a": 21,
      "fc": 4,
      "id": 180,
      "k": "HFn",
      "l": "HACCP number of HF alarm type recorded",
      "max": 255,
      "min": 0,
      "t": "u16"
    },
    {
      "a": 14,
      "fc": 2,
      "id": 181,
      "k": "HI",
      "l": "High temperature alarm (AH)",
      "max": 5,
      "min": 5,
      "t": "bit"
    },
    {
      "a": 16,
      "fc": 2,
      "id": 182,
      "k": "HI2",
      "l": "High temperature alarm (AH2)",
      "max": 5,
      "min": 5,
      "t": "bit"
    },
    {
      "a": 79,
      "fc": 4,
      "id": 183,
      "k": "HMb",
      "l": "Number of hours the unit has worked since last reset (in thousands of hours)",
      "max": 5,
      "min": 5,
      "t": "u16"
    },
    {
      "a": 386,
      "fc": 3,
      "id": 184,
      "k": "HMc",
      "l": "Unit Working Days threshold to trigger a maintenance warning",
      "max": 3650,
      "min": 0,
      "t": "u16",
      "w": 1
    },
    {
      "a": 80,
      "fc": 4,
      "id": 185,
      "k": "HMd",
      "l": "Number of Day since last maintenence reset",
      "max": 5,
      "min": 5,
      "t": "u16"
    },
    {
      "a": 385,
      "fc": 3,
      "id": 186,
      "k": "HMP",
      "l": "Working time threshold to trigger a maintenance warning (in thousands of hours)",
      "max": 45,
      "min": 0,
      "t": "u16",
      "w": 1
    },
    {
      "a": 17,
      "fc": 2,
      "id": 187,
      "k": "IA",
      "l": "Immediate alarm from external contact",
      "max": 5,
      "min": 5,
      "t": "bit"
    },
    {
      "a": 37,
      "fc": 1,
      "id": 188,
      "k": "In",
      "l": "Type of unit",
      "max": 5,
      "min": 5,
      "t": "bit"
    },
    {
      "a": 61,
      "fc": 1,
      "id": 189,
      "k": "Lht",
      "l": "Current light status is ON",
      "max": 5,
      "min": 5,
      "t": "bit",
      "w": 1
    },
    {
      "a": 13,
      "fc": 2,
      "id": 190,
      "k": "LO",
      "l": "Low temperature alarm (AL)",
      "max": 5,
      "min": 5,
      "t": "bit"
    },
    {
      "a": 15,
      "fc": 2,
      "id": 191,
      "k": "LO2",
      "l": "Low temperature alarm (AL2)",
      "max": 5,
      "min": 5,
      "t": "bit"
    },
    {
      "a": 29,
      "fc": 2,
      "id": 192,
      "k": "MA",
      "l": "Comm. error with the Main (only on Secondary)",
      "max": 5,
      "min": 5,
      "t": "bit"
    },
    {
      "a": 75,
      "fc": 1,
      "id": 193,
      "k": "ManCln",
      "l": "Clean command",
      "max": 5,
      "min": 5,
      "t": "u16",
      "w": 1
    },
    {
      "a": 42,
      "fc": 1,
      "id": 194,
      "k": "ManCnt",
      "l": "Continuous cycle Status",
      "max": 5,
      "min": 5,
      "t": "bit"
    },
    {
      "a": 88,
      "fc": 1,
      "id": 195,
      "k": "ManCnt_spv",
      "l": "Contìnuos Cycle Started/Stopped by Supervisor",
      "max": 5,
      "min": 5,
      "t": "bit",
      "w": 1
    },
    {
      "a": 23,
      "fc": 2,
      "id": 196,
      "k": "MOP",
      "l": "Max operating pressure (MOP) alarm",
      "max": 5,
      "min": 5,
      "t": "bit"
    },
    {
      "a": 39,
      "fc": 2,
      "id": 197,
      "k": "n1",
      "l": "Alarm on Secondary 1",
      "max": 5,
      "min": 5,
      "t": "bit"
    },
    {
      "a": 40,
      "fc": 2,
      "id": 198,
      "k": "n2",
      "l": "Alarm on Secondary 2",
      "max": 5,
      "min": 5,
      "t": "bit"
    },
    {
      "a": 41,
      "fc": 2,
      "id": 199,
      "k": "n3",
      "l": "Alarm on Secondary 3",
      "max": 5,
      "min": 5,
      "t": "bit"
    },
    {
      "a": 42,
      "fc": 2,
      "id": 200,
      "k": "n4",
      "l": "Alarm on Secondary 4",
      "max": 5,
      "min": 5,
      "t": "bit"
    },
    {
      "a": 43,
      "fc": 2,
      "id": 201,
      "k": "n5",
      "l": "Alarm on Secondary 5",
      "max": 5,
      "min": 5,
      "t": "bit"
    },
    {
      "a": 44,
      "fc": 2,
      "id": 202,
      "k": "n6",
      "l": "Alarm on Secondary 6",
      "max": 5,
      "min": 5,
      "t": "bit"
    },
    {
      "a": 45,
      "fc": 2,
      "id": 203,
      "k": "n7",
      "l": "Alarm on Secondary 7",
      "max": 5,
      "min": 5,
      "t": "bit"
    },
    {
      "a": 46,
      "fc": 2,
      "id": 204,
      "k": "n8",
      "l": "Alarm on Secondary 8",
      "max": 5,
      "min": 5,
      "t": "bit"
    },
    {
      "a": 47,
      "fc": 2,
      "id": 205,
      "k": "n9",
      "l": "Alarm on Secondary 9",
      "max": 5,
      "min": 5,
      "t": "bit"
    },
    {
      "a": 18,
      "fc": 1,
      "id": 206,
      "k": "ON",
      "l": "On/Off unit by keyboard",
      "max": 5,
      "min": 5,
      "t": "bit",
      "w": 1
    },
    {
      "a": 87,
      "fc": 1,
      "id": 207,
      "k": "ONS",
      "l": "Enable On/Off unit by supervisor",
      "max": 5,
      "min": 5,
      "t": "bit",
      "w": 1
    },
    {
      "a": 67,
      "fc": 2,
      "id": 208,
      "k": "OrAlrm",
      "l": "Alarms present",
      "max": 5,
      "min": 5,
      "t": "bit"
    },
    {
      "a": 134,
      "fc": 3,
      "id": 209,
      "k": "P3",
      "l": "SH setpoint",
      "max": 25,
      "min": 0,
      "s": 0.1,
      "t": "i16",
      "w": 1
    },
    {
      "a": 390,
      "fc": 3,
      "id": 210,
      "k": "P3A",
      "l": "Very low SH - Default setpoint",
      "max": 25,
      "min": 0,
      "s": 0.1,
      "t": "u16",
      "w": 1
    },
    {
      "a": 389,
      "fc": 3,
      "id": 211,
      "k": "P3d",
      "l": "Very low SH – Dynamic setpoint",
      "max": 25,
      "min": 0,
      "s": 0.1,
      "t": "u16",
      "w": 1
    },
    {
      "a": 117,
      "fc": 1,
      "id": 212,
      "k": "P3E",
      "l": "Very low SH – Activation command",
      "max": 5,
      "min": 5,
      "t": "bit",
      "w": 1
    },
    {
      "a": 122,
      "fc": 2,
      "id": 213,
      "k": "P3r",
      "l": "Very low SH - Running status",
      "max": 5,
      "min": 5,
      "t": "bit"
    },
    {
      "a": 136,
      "fc": 3,
      "id": 214,
      "k": "P5",
      "l": "Integral time for SH regulation",
      "max": 900,
      "min": 0,
      "t": "u16",
      "u": 22,
      "w": 1
    },
    {
      "a": 138,
      "fc": 3,
      "id": 215,
      "k": "P7",
      "l": "LowSH: low SH threshold",
      "min": -10,
      "s": 0.1,
      "t": "i16",
      "w": 1
    },
    {
      "a": 391,
      "fc": 3,
      "id": 216,
      "k": "P7d",
      "l": "Very low SH - Low SH threshold",
      "min": -10,
      "s": 0.1,
      "t": "u16",
      "w": 1
    },
    {
      "a": 139,
      "fc": 3,
      "id": 217,
      "k": "P8",
      "l": "LowSH: integration time",
      "max": 240,
      "min": 0,
      "s": 0.1,
      "t": "u16",
      "u": 22,
      "w": 1
    },
    {
      "a": 13,
      "fc": 4,
      "id": 218,
      "k": "Peu",
      "l": "Evap. pressure probe (PEu)",
      "max": 5,
      "min": 5,
      "s": 0.1,
      "t": "i16"
    },
    {
      "a": 144,
      "fc": 3,
      "id": 219,
      "k": "PH",
      "l": "Type of refrigerant",
      "max": 47,
      "min": 0,
      "t": "u16",
      "w": 1
    },
    {
      "a": 153,
      "fc": 3,
      "id": 220,
      "k": "PL3",
      "l": "LOP: alarm delay",
      "max": 240,
      "min": 0,
      "t": "u16",
      "u": 22,
      "w": 1
    },
    {
      "a": 146,
      "fc": 3,
      "id": 221,
      "k": "PM1",
      "l": "MOP: max saturated evap. temp. threshold",
      "max": 50,
      "min": -50,
      "s": 0.1,
      "t": "i16",
      "u": 1,
      "w": 1
    },
    {
      "a": 147,
      "fc": 3,
      "id": 222,
      "k": "PM2",
      "l": "MOP: integration time",
      "max": 800,
      "min": 0,
      "s": 0.1,
      "t": "u16",
      "u": 22,
      "w": 1
    },
    {
      "a": 34,
      "fc": 1,
      "id": 223,
      "k": "PM5",
      "l": "MOP: enable close solenoid valve",
      "max": 5,
      "min": 5,
      "t": "bit",
      "w": 1
    },
    {
      "a": 150,
      "fc": 3,
      "id": 224,
      "k": "PM6",
      "l": "MOP: max suction temp threshold used to stop MOP due to possible compressor overheating with reduced refrigerant flow",
      "max": 50,
      "min": -50,
      "s": 0.1,
      "t": "i16",
      "u": 1,
      "w": 1
    },
    {
      "a": 35,
      "fc": 1,
      "id": 225,
      "k": "PMP",
      "l": "Enable manual expansion valve positioning",
      "max": 5,
      "min": 5,
      "t": "bit",
      "w": 1
    },
    {
      "a": 155,
      "fc": 3,
      "id": 226,
      "k": "PMu",
      "l": "Manual valve position to set",
      "max": 100,
      "min": 0,
      "t": "u16",
      "w": 1
    },
    {
      "a": 72,
      "fc": 3,
      "id": 227,
      "k": "r1",
      "l": "Min temp. setpoint",
      "min": -50,
      "s": 0.1,
      "t": "i16",
      "u": 1,
      "w": 1
    },
    {
      "a": 73,
      "fc": 3,
      "id": 228,
      "k": "r2",
      "l": "Max temp setpoint",
      "max": 200,
      "s": 0.1,
      "t": "i16",
      "u": 1,
      "w": 1
    },
    {
      "a": 85,
      "fc": 1,
      "id": 229,
      "k": "rC",
      "l": "Temperature regulation operating mode",
      "max": 5,
      "min": 5,
      "t": "bit",
      "w": 1
    },
    {
      "a": 69,
      "fc": 3,
      "id": 230,
      "k": "rd",
      "l": "Set point differential (St)",
      "max": 99.9,
      "min": 0.1,
      "s": 0.1,
      "t": "u16",
      "u": 1,
      "w": 1
    },
    {
      "a": 0,
      "fc": 2,
      "id": 231,
      "k": "rE",
      "l": "Control probe",
      "max": 5,
      "min": 5,
      "t": "bit"
    },
    {
      "a": 84,
      "fc": 1,
      "id": 232,
      "k": "res",
      "l": "Reset all active alarms",
      "max": 5,
      "min": 5,
      "t": "bit",
      "w": 1
    },
    {
      "a": 39,
      "fc": 4,
      "id": 233,
      "k": "ResCnt",
      "l": "Number of restarts of MPXone application",
      "max": 5,
      "min": 5,
      "t": "u16"
    },
    {
      "a": 176,
      "fc": 3,
      "id": 234,
      "k": "rHA",
      "l": "Coeff. A for glass temp. probe estimate",
      "max": 20,
      "min": -20,
      "s": 0.1,
      "t": "i16",
      "u": 1,
      "w": 1
    },
    {
      "a": 177,
      "fc": 3,
      "id": 235,
      "k": "rHb",
      "l": "Coeff. B for glass temp. probe estimate",
      "max": 100,
      "min": 0,
      "t": "u16",
      "w": 1
    },
    {
      "a": 171,
      "fc": 3,
      "id": 236,
      "k": "rHd",
      "l": "Differential for anti-sweat heater modul.",
      "max": 20,
      "min": 0,
      "s": 0.1,
      "t": "i16",
      "u": 1,
      "w": 1
    },
    {
      "a": 170,
      "fc": 3,
      "id": 237,
      "k": "rHo",
      "l": "Off set for anti-sweat heater modul.",
      "max": 20,
      "min": -20,
      "s": 0.1,
      "t": "i16",
      "u": 1,
      "w": 1
    },
    {
      "a": 169,
      "fc": 3,
      "id": 238,
      "k": "rHt",
      "l": "Manual anti-sweat heater activation period",
      "max": 180,
      "min": 0,
      "t": "u16",
      "u": 23,
      "w": 1
    },
    {
      "a": 168,
      "fc": 3,
      "id": 239,
      "k": "rHu",
      "l": "Manual anti-sweat heater activation percentage (of period rHt)",
      "max": 100,
      "min": 0,
      "t": "u16",
      "u": 3,
      "w": 1
    },
    {
      "a": 7,
      "fc": 1,
      "id": 240,
      "k": "rIH",
      "l": "Config. start/stop continuous cycle digital input logic",
      "max": 5,
      "min": 5,
      "t": "bit",
      "w": 1
    },
    {
      "a": 83,
      "fc": 1,
      "id": 241,
      "k": "rOAA",
      "l": "HotGas digital output logic",
      "max": 5,
      "min": 5,
      "t": "bit",
      "w": 1
    },
    {
      "a": 73,
      "fc": 1,
      "id": 242,
      "k": "rOQ",
      "l": "Config. Anti-sweat heaters digital output logic",
      "max": 5,
      "min": 5,
      "t": "bit",
      "w": 1
    },
    {
      "a": 2,
      "fc": 4,
      "id": 243,
      "k": "Sd",
      "l": "Defrost temp. probe (Sd)",
      "max": 5,
      "min": 5,
      "s": 0.1,
      "t": "i16",
      "u": 1
    },
    {
      "a": 6,
      "fc": 4,
      "id": 244,
      "k": "Sd2",
      "l": "Defrost temp. probe 2 (Sd2)",
      "max": 5,
      "min": 5,
      "s": 0.1,
      "t": "i16",
      "u": 1
    },
    {
      "a": 12,
      "fc": 4,
      "id": 245,
      "k": "Sdp",
      "l": "Dewpoint value (Sdp)",
      "max": 5,
      "min": 5,
      "s": 0.1,
      "t": "i16",
      "u": 1
    },
    {
      "a": 1,
      "fc": 4,
      "id": 246,
      "k": "SM",
      "l": "Air off temp. probe (Sm)",
      "max": 5,
      "min": 5,
      "s": 0.1,
      "t": "i16",
      "u": 1
    },
    {
      "a": 161,
      "fc": 3,
      "id": 247,
      "k": "Sn",
      "l": "Num. of Secondaries in the local network",
      "min": 0,
      "t": "u16"
    },
    {
      "a": 3,
      "fc": 4,
      "id": 248,
      "k": "Sr",
      "l": "Air on temp. probe (Sr)",
      "max": 5,
      "min": 5,
      "s": 0.1,
      "t": "i16",
      "u": 1
    },
    {
      "a": 67,
      "fc": 3,
      "id": 249,
      "k": "St",
      "l": "Regulation setpoint",
      "s": 0.1,
      "t": "i16",
      "u": 1,
      "w": 1
    },
    {
      "a": 0,
      "fc": 4,
      "id": 250,
      "k": "Sv",
      "l": "Virtual probe value used for temperature regulation",
      "max": 5,
      "min": 5,
      "s": 0.1,
      "t": "i16",
      "u": 1
    },
    {
      "a": 208,
      "fc": 3,
      "id": 251,
      "k": "tc_y__",
      "l": "RTC configuration - Year",
      "max": 99,
      "min": 0,
      "t": "u16",
      "w": 1
    },
    {
      "a": 206,
      "fc": 3,
      "id": 252,
      "k": "tc_d__",
      "l": "RTC configuration - Day of month",
      "max": 31,
      "min": 1,
      "t": "u16",
      "w": 1
    },
    {
      "a": 210,
      "fc": 3,
      "id": 253,
      "k": "tc_m__",
      "l": "RTC configuration - Month",
      "max": 59,
      "min": 0,
      "t": "u16",
      "u": 23,
      "w": 1
    },
    {
      "a": 207,
      "fc": 3,
      "id": 254,
      "k": "tc_M__",
      "l": "RTC configuration - Month",
      "max": 12,
      "min": 1,
      "t": "u16",
      "w": 1
    },
    {
      "a": 209,
      "fc": 3,
      "id": 255,
      "k": "tc_h__",
      "l": "RTC configuration - Hour",
      "max": 23,
      "min": 0,
      "t": "u16",
      "u": 24,
      "w": 1
    },
    {
      "a": 182,
      "fc": 3,
      "id": 256,
      "k": "td1_d__",
      "l": "defrost 1 - Day/s",
      "max": 11,
      "min": 0,
      "t": "u16",
      "w": 1
    },
    {
      "a": 184,
      "fc": 3,
      "id": 257,
      "k": "td1_m__",
      "l": "defrost 1 - Minute",
      "max": 59,
      "min": 0,
      "t": "u16",
      "u": 23,
      "w": 1
    },
    {
      "a": 183,
      "fc": 3,
      "id": 258,
      "k": "td1_h__",
      "l": "defrost 1 - Hour",
      "max": 23,
      "min": 0,
      "t": "u16",
      "u": 24,
      "w": 1
    },
    {
      "a": 62,
      "fc": 1,
      "id": 259,
      "k": "td1_P__",
      "l": "defrost 1 - Power Defrost",
      "max": 1,
      "min": 0,
      "t": "u16",
      "w": 1
    },
    {
      "a": 185,
      "fc": 3,
      "id": 260,
      "k": "td2_d__",
      "l": "defrost 2 - Day/s",
      "max": 11,
      "min": 0,
      "t": "u16",
      "w": 1
    },
    {
      "a": 187,
      "fc": 3,
      "id": 261,
      "k": "td2_m__",
      "l": "defrost 2 - Minute",
      "max": 59,
      "min": 0,
      "t": "u16",
      "u": 23,
      "w": 1
    },
    {
      "a": 186,
      "fc": 3,
      "id": 262,
      "k": "td2_h__",
      "l": "defrost 2 - Hour",
      "max": 23,
      "min": 0,
      "t": "u16",
      "u": 24,
      "w": 1
    },
    {
      "a": 63,
      "fc": 1,
      "id": 263,
      "k": "td2_P__",
      "l": "defrost 2 - Power Defrost",
      "max": 1,
      "min": 0,
      "t": "u16",
      "w": 1
    },
    {
      "a": 77,
      "fc": 3,
      "id": 264,
      "k": "Tdoor",
      "l": "Door open: alarm delay",
      "max": 240,
      "min": 1,
      "t": "u16",
      "u": 23,
      "w": 1
    },
    {
      "a": 236,
      "fc": 3,
      "id": 265,
      "k": "tE1-d",
      "l": "End time band 1 - day",
      "max": 11,
      "min": 0,
      "t": "u16",
      "w": 1
    },
    {
      "a": 237,
      "fc": 3,
      "id": 266,
      "k": "tE1-h",
      "l": "End time band 1 - hour",
      "max": 23,
      "min": 0,
      "t": "u16",
      "u": 24,
      "w": 1
    },
    {
      "a": 238,
      "fc": 3,
      "id": 267,
      "k": "tE1-m",
      "l": "End time band 1 - minute",
      "max": 59,
      "min": 0,
      "t": "u16",
      "u": 23,
      "w": 1
    },
    {
      "a": 247,
      "fc": 3,
      "id": 268,
      "k": "tE2-d",
      "l": "End time band 2 - day",
      "max": 11,
      "min": 0,
      "t": "u16",
      "w": 1
    },
    {
      "a": 248,
      "fc": 3,
      "id": 269,
      "k": "tE2-h",
      "l": "End time band 2 - hour",
      "max": 23,
      "min": 0,
      "t": "u16",
      "u": 24,
      "w": 1
    },
    {
      "a": 249,
      "fc": 3,
      "id": 270,
      "k": "tE2-m",
      "l": "End time band 2 - minute",
      "max": 59,
      "min": 0,
      "t": "u16",
      "u": 23,
      "w": 1
    },
    {
      "a": 253,
      "fc": 3,
      "id": 271,
      "k": "tE3-d",
      "l": "End time band 3 - day",
      "max": 11,
      "min": 0,
      "t": "u16",
      "w": 1
    },
    {
      "a": 254,
      "fc": 3,
      "id": 272,
      "k": "tE3-h",
      "l": "End time band 3 - hour",
      "max": 23,
      "min": 0,
      "t": "u16",
      "u": 24,
      "w": 1
    },
    {
      "a": 255,
      "fc": 3,
      "id": 273,
      "k": "tE3-m",
      "l": "End time band 3 - minute",
      "max": 59,
      "min": 0,
      "t": "u16",
      "u": 23,
      "w": 1
    },
    {
      "a": 233,
      "fc": 3,
      "id": 274,
      "k": "tS1-d",
      "l": "Start time band 1 - day",
      "max": 11,
      "min": 0,
      "t": "u16",
      "w": 1
    },
    {
      "a": 234,
      "fc": 3,
      "id": 275,
      "k": "tS1-h",
      "l": "Start time band 1 - hour",
      "max": 23,
      "min": 0,
      "t": "u16",
      "u": 24,
      "w": 1
    },
    {
      "a": 235,
      "fc": 3,
      "id": 276,
      "k": "tS1-m",
      "l": "Start time band 1 - minute",
      "max": 59,
      "min": 0,
      "t": "u16",
      "u": 23,
      "w": 1
    },
    {
      "a": 244,
      "fc": 3,
      "id": 277,
      "k": "tS2-d",
      "l": "Start time band 2 - day",
      "max": 11,
      "min": 0,
      "t": "u16",
      "w": 1
    },
    {
      "a": 245,
      "fc": 3,
      "id": 278,
      "k": "tS2-h",
      "l": "Start time band 2 - hour",
      "max": 23,
      "min": 0,
      "t": "u16",
      "u": 24,
      "w": 1
    },
    {
      "a": 246,
      "fc": 3,
      "id": 279,
      "k": "tS2-m",
      "l": "Start time band 2 - minute",
      "max": 59,
      "min": 0,
      "t": "u16",
      "u": 23,
      "w": 1
    },
    {
      "a": 250,
      "fc": 3,
      "id": 280,
      "k": "tS3-d",
      "l": "Start time band 3 - day",
      "max": 11,
      "min": 0,
      "t": "u16",
      "w": 1
    },
    {
      "a": 251,
      "fc": 3,
      "id": 281,
      "k": "tS3-h",
      "l": "Start time band 3 - hour",
      "max": 23,
      "min": 0,
      "t": "u16",
      "u": 24,
      "w": 1
    },
    {
      "a": 252,
      "fc": 3,
      "id": 282,
      "k": "tS3-m",
      "l": "Start time band 3 - minute",
      "max": 59,
      "min": 0,
      "t": "u16",
      "u": 23,
      "w": 1
    },
    {
      "a": 30,
      "fc": 2,
      "id": 283,
      "k": "u1",
      "l": "Comm. error with the Secondary 1 (only on Main)",
      "max": 5,
      "min": 5,
      "t": "bit"
    },
    {
      "a": 31,
      "fc": 2,
      "id": 284,
      "k": "u2",
      "l": "Comm. error with the Secondary 2 (only on Main)",
      "max": 5,
      "min": 5,
      "t": "bit"
    },
    {
      "a": 32,
      "fc": 2,
      "id": 285,
      "k": "u3",
      "l": "Comm. error with the Secondary 3 (only on Main)",
      "max": 5,
      "min": 5,
      "t": "bit"
    },
    {
      "a": 33,
      "fc": 2,
      "id": 286,
      "k": "u4",
      "l": "Comm. error with the Secondary 4 (only on Main)",
      "max": 5,
      "min": 5,
      "t": "bit"
    },
    {
      "a": 34,
      "fc": 2,
      "id": 287,
      "k": "u5",
      "l": "Comm. error with the Secondary 5 (only on Main)",
      "max": 5,
      "min": 5,
      "t": "bit"
    },
    {
      "a": 35,
      "fc": 2,
      "id": 288,
      "k": "u6",
      "l": "Comm. error with the Secondary 6 (only on Main)",
      "max": 5,
      "min": 5,
      "t": "bit"
    },
    {
      "a": 36,
      "fc": 2,
      "id": 289,
      "k": "u7",
      "l": "Comm. error with the Secondary 7 (only on Main)",
      "max": 5,
      "min": 5,
      "t": "bit"
    },
    {
      "a": 37,
      "fc": 2,
      "id": 290,
      "k": "u8",
      "l": "Comm. error with the Secondary 8 (only on Main)",
      "max": 5,
      "min": 5,
      "t": "bit"
    },
    {
      "a": 38,
      "fc": 2,
      "id": 291,
      "k": "u9",
      "l": "Comm. error with the Secondary 9 (only on Main)",
      "max": 5,
      "min": 5,
      "t": "bit"
    },
    {
      "a": 96,
      "fc": 2,
      "id": 292,
      "k": "uGH",
      "l": "Generic warning 1 - High",
      "max": 5,
      "min": 5,
      "t": "bit"
    },
    {
      "a": 97,
      "fc": 2,
      "id": 293,
      "k": "uGL",
      "l": "Generic Warning 1 - Low",
      "max": 5,
      "min": 5,
      "t": "bit"
    },
    {
      "a": 34,
      "fc": 4,
      "id": 294,
      "k": "UID_3",
      "l": "UID : byte 3",
      "max": 5,
      "min": 5,
      "t": "u16"
    },
    {
      "a": 35,
      "fc": 4,
      "id": 295,
      "k": "UID_4",
      "l": "UID : byte 4",
      "max": 5,
      "min": 5,
      "t": "u16"
    },
    {
      "a": 36,
      "fc": 4,
      "id": 296,
      "k": "UID_5",
      "l": "UID : byte 5",
      "max": 5,
      "min": 5,
      "t": "u16"
    },
    {
      "a": 37,
      "fc": 4,
      "id": 297,
      "k": "UID_6",
      "l": "UID : byte 6",
      "max": 5,
      "min": 5,
      "t": "u16"
    },
    {
      "a": 38,
      "fc": 4,
      "id": 298,
      "k": "UID_7",
      "l": "UID : byte 7",
      "max": 5,
      "min": 5,
      "t": "u16"
    },
    {
      "a": 88,
      "fc": 2,
      "id": 299,
      "k": "UnitOn",
      "l": "Unit ON status",
      "max": 5,
      "min": 5,
      "t": "bit"
    },
    {
      "a": 40,
      "fc": 4,
      "id": 300,
      "k": "UnitStatus",
      "l": "Unit Status",
      "max": 11,
      "min": 0,
      "t": "u16"
    }
  ],
  "schema": 2,
  "vendor": "carel"
}
