{
  "bitmasks": {
    "sw1": [
      {
        "bp": 0,
        "l": "Saida COMP ligada"
      },
      {
        "bp": 1,
        "l": "Saida FAN ligada"
      },
      {
        "bp": 2,
        "l": "Saida DEFR ligada"
      },
      {
        "bp": 3,
        "l": "Saida AUX ligada"
      },
      {
        "bp": 4,
        "l": "Saida VCC COMP ligada"
      },
      {
        "bp": 5,
        "l": "Saida VSF FAN ligada"
      },
      {
        "bp": 6,
        "l": "Entrada digital 1"
      },
      {
        "bp": 7,
        "l": "Entrada digital 2"
      },
      {
        "bp": 8,
        "l": "Processo: Delay inicial"
      },
      {
        "bp": 9,
        "l": "Processo: Refrigeracao/Aquecimento"
      },
      {
        "bp": 10,
        "l": "Processo: Pre-degelo"
      },
      {
        "bp": 11,
        "l": "Processo: Degelo"
      },
      {
        "bp": 12,
        "l": "Processo: Drenagem"
      },
      {
        "bp": 13,
        "l": "Processo: Fan-delay"
      },
      {
        "bp": 14,
        "l": "Processo: Combined Defrost Delay"
      },
      {
        "bp": 15,
        "l": "Processo: Standby"
      }
    ],
    "sw2": [
      {
        "bp": 0,
        "l": "Erro sensor S1"
      },
      {
        "bp": 1,
        "l": "Erro sensor S2"
      },
      {
        "bp": 2,
        "l": "Erro sensor S3"
      },
      {
        "bp": 3,
        "l": "Erro sensor S4"
      },
      {
        "bp": 4,
        "l": "Relogio desprogramado"
      },
      {
        "bp": 5,
        "l": "Datalogger corrompido"
      },
      {
        "bp": 6,
        "l": "Reconfigurar valores das funcoes"
      },
      {
        "bp": 7,
        "l": "Porta aberta"
      },
      {
        "bp": 8,
        "l": "Alarme manutencao compressor"
      },
      {
        "bp": 9,
        "l": "Alarme tensao alta"
      },
      {
        "bp": 10,
        "l": "Alarme tensao baixa"
      },
      {
        "bp": 11,
        "l": "Novo alarme HACCP"
      },
      {
        "bp": 12,
        "l": "Evento pressao baixa"
      },
      {
        "bp": 13,
        "l": "Alarme pressao baixa"
      },
      {
        "bp": 14,
        "l": "Evento pressao alta"
      },
      {
        "bp": 15,
        "l": "Alarme pressao alta"
      }
    ],
    "sw3": [
      {
        "bp": 0,
        "l": "Alarme temp alta S1"
      },
      {
        "bp": 1,
        "l": "Alarme temp baixa S1"
      },
      {
        "bp": 2,
        "l": "Alarme temp alta condensador S3"
      },
      {
        "bp": 3,
        "l": "Alarme temp alta condensador S3 desliga saida"
      },
      {
        "bp": 4,
        "l": "Alarme porta aberta"
      },
      {
        "bp": 5,
        "l": "Alarme externo (entrada digital)"
      },
      {
        "bp": 6,
        "l": "Alarme tempo compressor sem atingir setpoint"
      },
      {
        "bp": 7,
        "l": "Alarme degelo encerrado por tempo"
      },
      {
        "bp": 8,
        "l": "Fast Freezing ativado"
      },
      {
        "bp": 9,
        "l": "Modo Economico ativado"
      },
      {
        "bp": 10,
        "l": "Datalogger ligado"
      },
      {
        "bp": 11,
        "l": "Datalogger cheio"
      },
      {
        "bp": 12,
        "l": "Datalogger sobrescrevendo"
      },
      {
        "bp": 13,
        "l": "Modo Refr/Aquec (0=Refrig, 1=Aquec)"
      },
      {
        "bp": 14,
        "l": "Sensor S3 habilitado"
      },
      {
        "bp": 15,
        "l": "Sensor S4 habilitado"
      }
    ]
  },
  "bus": {
    "baud": 9600,
    "bits": 8,
    "endian": "L",
    "parity": "N",
    "stop": 1
  },
  "deviceClass": "refrigeration-controller",
  "family": "tc-970e",
  "model": "TC-970E Log +Eco",
  "profileId": "fullgauge-modbus-tc970e-log-eco-v1.0.0",
  "protocol": "modbus-rtu",
  "quirks": {
    "reqSpacingMs": 100
  },
  "regs": [
    {
      "a": 0,
      "cat": 10,
      "fc": 3,
      "g": 15,
      "id": 1,
      "k": "F00",
      "l": "[op_mode] Modo de operacao do controlador (0=Refrig, 1=Aquec, 2=Refrig/Aquec)",
      "max": 2,
      "min": 0,
      "t": "u16",
      "w": 1
    },
    {
      "a": 1,
      "cat": 2,
      "fc": 3,
      "g": 15,
      "id": 2,
      "k": "F01",
      "l": "[setp] Temperatura desejada (setpoint)",
      "max": 1050,
      "min": -500,
      "s": 0.1,
      "t": "i16",
      "u": 1,
      "w": 1
    },
    {
      "a": 2,
      "cat": 2,
      "fc": 3,
      "g": 15,
      "id": 3,
      "k": "F02",
      "l": "[setp_eco] Temperatura desejada (setpoint economico)",
      "max": 1050,
      "min": -500,
      "s": 0.1,
      "t": "i16",
      "u": 1,
      "w": 1
    },
    {
      "a": 3,
      "cat": 2,
      "fc": 3,
      "g": 15,
      "id": 4,
      "k": "F03",
      "l": "[setp_min] Minimo de setpoint permitido ao usuario",
      "max": 1050,
      "min": -500,
      "s": 0.1,
      "t": "i16",
      "u": 1,
      "w": 1
    },
    {
      "a": 4,
      "cat": 2,
      "fc": 3,
      "g": 15,
      "id": 5,
      "k": "F04",
      "l": "[setp_max] Maximo de setpoint permitido ao usuario",
      "max": 1050,
      "min": -500,
      "s": 0.1,
      "t": "i16",
      "u": 1,
      "w": 1
    },
    {
      "a": 5,
      "cat": 10,
      "fc": 3,
      "g": 15,
      "id": 6,
      "k": "F05",
      "l": "[diff_setp] Diferencial do setpoint operacao (refrigeracao)",
      "max": 200,
      "min": 1,
      "s": 0.1,
      "t": "i16",
      "u": 1,
      "w": 1
    },
    {
      "a": 6,
      "cat": 10,
      "fc": 3,
      "g": 15,
      "id": 7,
      "k": "F06",
      "l": "[diff_setp_eco] Diferencial do setpoint economico (refrigeracao)",
      "max": 200,
      "min": 1,
      "s": 0.1,
      "t": "i16",
      "u": 1,
      "w": 1
    },
    {
      "a": 7,
      "cat": 10,
      "fc": 3,
      "g": 15,
      "id": 8,
      "k": "F07",
      "l": "[diff_setp_h] Diferencial do setpoint operacao (aquecimento)",
      "max": 200,
      "min": 1,
      "s": 0.1,
      "t": "i16",
      "u": 1,
      "w": 1
    },
    {
      "a": 8,
      "cat": 10,
      "fc": 3,
      "g": 15,
      "id": 9,
      "k": "F08",
      "l": "[diff_setp_eco_h] Diferencial do setpoint economico (aquecimento)",
      "max": 200,
      "min": 1,
      "s": 0.1,
      "t": "i16",
      "u": 1,
      "w": 1
    },
    {
      "a": 9,
      "cat": 10,
      "fc": 3,
      "g": 15,
      "id": 10,
      "k": "F09",
      "l": "[eco_start_wd] Horario inicio modo economico (Seg-Sex) [min desde 00:00; 1440=Off]",
      "max": 1440,
      "min": 0,
      "t": "u16",
      "u": 23,
      "w": 1
    },
    {
      "a": 10,
      "cat": 10,
      "fc": 3,
      "g": 15,
      "id": 11,
      "k": "F10",
      "l": "[eco_start_sat] Horario inicio modo economico (Sabado)",
      "max": 1440,
      "min": 0,
      "t": "u16",
      "u": 23,
      "w": 1
    },
    {
      "a": 11,
      "cat": 10,
      "fc": 3,
      "g": 15,
      "id": 12,
      "k": "F11",
      "l": "[eco_start_sun] Horario inicio modo economico (Domingo)",
      "max": 1440,
      "min": 0,
      "t": "u16",
      "u": 23,
      "w": 1
    },
    {
      "a": 12,
      "cat": 10,
      "fc": 3,
      "g": 15,
      "id": 13,
      "k": "F12",
      "l": "[eco_delta_low] Delta (S3-S1) abaixo do qual ativa setpoint economico",
      "max": 200,
      "min": 1,
      "s": 0.1,
      "t": "i16",
      "u": 1,
      "w": 1
    },
    {
      "a": 13,
      "cat": 10,
      "fc": 3,
      "g": 15,
      "id": 14,
      "k": "F13",
      "l": "[eco_delta_high] Delta (S3-S1) acima do qual ativa setpoint normal",
      "max": 200,
      "min": 1,
      "s": 0.1,
      "t": "i16",
      "u": 1,
      "w": 1
    },
    {
      "a": 14,
      "cat": 10,
      "fc": 3,
      "g": 15,
      "id": 15,
      "k": "F14",
      "l": "[eco_max_time] Tempo maximo no modo economico [min; 0=Off]",
      "max": 999,
      "min": 0,
      "t": "u16",
      "u": 23,
      "w": 1
    },
    {
      "a": 15,
      "cat": 2,
      "fc": 3,
      "g": 15,
      "id": 16,
      "k": "F15",
      "l": "[ff_limit] Limite temp Fast Freezing",
      "max": 1050,
      "min": -500,
      "s": 0.1,
      "t": "i16",
      "u": 1,
      "w": 1
    },
    {
      "a": 16,
      "cat": 10,
      "fc": 3,
      "g": 15,
      "id": 17,
      "k": "F16",
      "l": "[ff_max_time] Tempo maximo Fast Freezing [min; 0=Off]",
      "max": 999,
      "min": 0,
      "t": "u16",
      "u": 23,
      "w": 1
    },
    {
      "a": 17,
      "cat": 10,
      "fc": 3,
      "g": 15,
      "id": 18,
      "k": "F17",
      "l": "[startup_delay] Tempo retardo ao energizar [min; 0=Off]",
      "max": 999,
      "min": 0,
      "t": "u16",
      "u": 23,
      "w": 1
    },
    {
      "a": 18,
      "cat": 10,
      "fc": 3,
      "g": 15,
      "id": 19,
      "k": "F18",
      "l": "[defr_type] Tipo de degelo (0=Resistivo, 1=Gas quente, 2=Parada)",
      "max": 2,
      "min": 0,
      "t": "u16",
      "w": 1
    },
    {
      "a": 19,
      "cat": 10,
      "fc": 3,
      "g": 15,
      "id": 20,
      "k": "F19",
      "l": "[defr_start_cond] Condicao inicio degelo (0=Off,1=intervalo,2-4=temp,5=horario)",
      "max": 5,
      "min": 0,
      "t": "u16",
      "w": 1
    },
    {
      "a": 20,
      "cat": 10,
      "fc": 3,
      "g": 15,
      "id": 21,
      "k": "F20",
      "l": "[defr_interval_r] Intervalo/max sem degelos (refrig) [min]",
      "max": 9999,
      "min": 1,
      "t": "u16",
      "u": 23,
      "w": 1
    },
    {
      "a": 21,
      "cat": 10,
      "fc": 3,
      "g": 15,
      "id": 22,
      "k": "F21",
      "l": "[defr_interval_h] Intervalo/max sem degelos (aquec) [min]",
      "max": 9999,
      "min": 1,
      "t": "u16",
      "u": 23,
      "w": 1
    },
    {
      "a": 22,
      "cat": 10,
      "fc": 3,
      "g": 15,
      "id": 23,
      "k": "F22",
      "l": "[defr_add_time] Tempo adicional ao final do 1o ciclo refrig [min; 0=Off]",
      "max": 999,
      "min": 0,
      "t": "u16",
      "u": 23,
      "w": 1
    },
    {
      "a": 23,
      "cat": 10,
      "fc": 3,
      "g": 15,
      "id": 24,
      "k": "F23",
      "l": "[defr_evap_start] Temp evaporador (S2/S3) inicio degelo se F19=2/3/4",
      "max": 1050,
      "min": -500,
      "s": 0.1,
      "t": "i16",
      "u": 1,
      "w": 1
    },
    {
      "a": 24,
      "cat": 10,
      "fc": 3,
      "g": 15,
      "id": 25,
      "k": "F24",
      "l": "[defr_delta_s1s2] Delta (S1-S2) inicio degelo se F19=3/4",
      "max": 1050,
      "min": -500,
      "s": 0.1,
      "t": "i16",
      "u": 1,
      "w": 1
    },
    {
      "a": 25,
      "cat": 10,
      "fc": 3,
      "g": 15,
      "id": 26,
      "k": "F25",
      "l": "[defr_confirm_t] Tempo confirmacao temp baixa (S2/S3) pra pre-degelo [min; 0=Off]",
      "max": 999,
      "min": 0,
      "t": "u16",
      "u": 23,
      "w": 1
    },
    {
      "a": 26,
      "cat": 10,
      "fc": 3,
      "g": 15,
      "id": 27,
      "k": "F26",
      "l": "[defr_on_power] Degelo ao energizar controlador (0=Off, 1=On)",
      "max": 1,
      "min": 0,
      "t": "u16",
      "w": 1
    },
    {
      "a": 27,
      "cat": 10,
      "fc": 3,
      "g": 15,
      "id": 28,
      "k": "F27",
      "l": "[smooth_defrost] Smooth Defrost se F18=0 [%; 100=Off]",
      "max": 100,
      "min": 10,
      "t": "u16",
      "u": 3,
      "w": 1
    },
    {
      "a": 28,
      "cat": 10,
      "fc": 3,
      "g": 15,
      "id": 29,
      "k": "F28",
      "l": "[defr_cnt_wd] Numero degelos/dia (Seg-Sex) se F19=5 (validos:1,2,3,4,6,8,12)",
      "max": 12,
      "min": 1,
      "t": "u16",
      "w": 1
    },
    {
      "a": 29,
      "cat": 10,
      "fc": 3,
      "g": 15,
      "id": 30,
      "k": "F29",
      "l": "[defr_start_mon] Horario inicio degelo (Segunda) se F19=5",
      "max": 1440,
      "min": 0,
      "t": "u16",
      "u": 23,
      "w": 1
    },
    {
      "a": 30,
      "cat": 10,
      "fc": 3,
      "g": 15,
      "id": 31,
      "k": "F30",
      "l": "[defr_start_tue] Horario inicio degelo (Terca) se F19=5",
      "max": 1440,
      "min": 0,
      "t": "u16",
      "u": 23,
      "w": 1
    },
    {
      "a": 31,
      "cat": 10,
      "fc": 3,
      "g": 15,
      "id": 32,
      "k": "F31",
      "l": "[defr_start_wed] Horario inicio degelo (Quarta) se F19=5",
      "max": 1440,
      "min": 0,
      "t": "u16",
      "u": 23,
      "w": 1
    },
    {
      "a": 32,
      "cat": 10,
      "fc": 3,
      "g": 15,
      "id": 33,
      "k": "F32",
      "l": "[defr_start_thu] Horario inicio degelo (Quinta) se F19=5",
      "max": 1440,
      "min": 0,
      "t": "u16",
      "u": 23,
      "w": 1
    },
    {
      "a": 33,
      "cat": 10,
      "fc": 3,
      "g": 15,
      "id": 34,
      "k": "F33",
      "l": "[defr_start_fri] Horario inicio degelo (Sexta) se F19=5",
      "max": 1440,
      "min": 0,
      "t": "u16",
      "u": 23,
      "w": 1
    },
    {
      "a": 34,
      "cat": 10,
      "fc": 3,
      "g": 15,
      "id": 35,
      "k": "F34",
      "l": "[defr_cnt_sat] Numero degelos/dia (Sabado) se F19=5",
      "max": 12,
      "min": 1,
      "t": "u16",
      "w": 1
    },
    {
      "a": 35,
      "cat": 10,
      "fc": 3,
      "g": 15,
      "id": 36,
      "k": "F35",
      "l": "[defr_start_sat] Horario inicio degelo (Sabado) se F19=5",
      "max": 1440,
      "min": 0,
      "t": "u16",
      "u": 23,
      "w": 1
    },
    {
      "a": 36,
      "cat": 10,
      "fc": 3,
      "g": 15,
      "id": 37,
      "k": "F36",
      "l": "[defr_cnt_sun] Numero degelos/dia (Domingo) se F19=5",
      "max": 12,
      "min": 1,
      "t": "u16",
      "w": 1
    },
    {
      "a": 37,
      "cat": 10,
      "fc": 3,
      "g": 15,
      "id": 38,
      "k": "F37",
      "l": "[defr_start_sun] Horario inicio degelo (Domingo) se F19=5",
      "max": 1440,
      "min": 0,
      "t": "u16",
      "u": 23,
      "w": 1
    },
    {
      "a": 38,
      "cat": 10,
      "fc": 3,
      "g": 15,
      "id": 39,
      "k": "F38",
      "l": "[predefr_time] Tempo pre-degelo (recolhimento do gas) [min; 0=Off]",
      "max": 999,
      "min": 0,
      "t": "u16",
      "u": 23,
      "w": 1
    },
    {
      "a": 39,
      "cat": 10,
      "fc": 3,
      "g": 15,
      "id": 40,
      "k": "F39",
      "l": "[defr_evap_end] Temp evap (S2/S3) fim degelo",
      "max": 1050,
      "min": -500,
      "s": 0.1,
      "t": "i16",
      "u": 1,
      "w": 1
    },
    {
      "a": 40,
      "cat": 10,
      "fc": 3,
      "g": 15,
      "id": 41,
      "k": "F40",
      "l": "[defr_amb_end] Temp ambiente (S1) fim degelo",
      "max": 1050,
      "min": -500,
      "s": 0.1,
      "t": "i16",
      "u": 1,
      "w": 1
    },
    {
      "a": 41,
      "cat": 10,
      "fc": 3,
      "g": 15,
      "id": 42,
      "k": "F41",
      "l": "[defr_max_time] Tempo maximo degelo por seguranca [min]",
      "max": 999,
      "min": 1,
      "t": "u16",
      "u": 23,
      "w": 1
    },
    {
      "a": 42,
      "cat": 10,
      "fc": 3,
      "g": 15,
      "id": 43,
      "k": "F42",
      "l": "[drain_time] Tempo dreno (gotejamento agua) [min; 0=Off]",
      "max": 999,
      "min": 0,
      "t": "u16",
      "u": 23,
      "w": 1
    },
    {
      "a": 43,
      "cat": 10,
      "fc": 3,
      "g": 15,
      "id": 44,
      "k": "F43",
      "l": "[tray_defrost] Habilita descongelamento da bandeja",
      "max": 2,
      "min": 0,
      "t": "u16",
      "w": 1
    },
    {
      "a": 44,
      "cat": 10,
      "fc": 3,
      "g": 15,
      "id": 45,
      "k": "F44",
      "l": "[fan_type] Tipo de ventilador",
      "max": 2,
      "min": 0,
      "t": "u16",
      "w": 1
    },
    {
      "a": 45,
      "cat": 10,
      "fc": 3,
      "g": 15,
      "id": 46,
      "k": "F45",
      "l": "[fan_mode] Modo de operacao do ventilador",
      "max": 4,
      "min": 0,
      "t": "u16",
      "w": 1
    },
    {
      "a": 46,
      "cat": 10,
      "fc": 3,
      "g": 15,
      "id": 47,
      "k": "F46",
      "l": "[fan_on_time] Tempo ventilador ligado se F45=0/4 [min]",
      "max": 999,
      "min": 1,
      "t": "u16",
      "u": 23,
      "w": 1
    },
    {
      "a": 47,
      "cat": 10,
      "fc": 3,
      "g": 15,
      "id": 48,
      "k": "F47",
      "l": "[fan_off_time] Tempo ventilador desligado se F45=0 [min]",
      "max": 999,
      "min": 1,
      "t": "u16",
      "u": 23,
      "w": 1
    },
    {
      "a": 48,
      "cat": 10,
      "fc": 3,
      "g": 15,
      "id": 49,
      "k": "F48",
      "l": "[fan_return_t] Temp evaporador retorno ventilador apos drenagem",
      "max": 1050,
      "min": -500,
      "s": 0.1,
      "t": "i16",
      "u": 1,
      "w": 1
    },
    {
      "a": 49,
      "cat": 10,
      "fc": 3,
      "g": 15,
      "id": 50,
      "k": "F49",
      "l": "[fan_delay_max] Tempo max retorno vent apos dreno (fan-delay) [min; 0=Off]",
      "max": 999,
      "min": 0,
      "t": "u16",
      "u": 23,
      "w": 1
    },
    {
      "a": 50,
      "cat": 10,
      "fc": 3,
      "g": 15,
      "id": 51,
      "k": "F50",
      "l": "[fan_stop_high_t] Parada vent por temp alta evap (S2)",
      "max": 1050,
      "min": -500,
      "s": 0.1,
      "t": "i16",
      "u": 1,
      "w": 1
    },
    {
      "a": 51,
      "cat": 10,
      "fc": 3,
      "g": 15,
      "id": 52,
      "k": "F51",
      "l": "[fan_door_open_s] Tempo porta aberta pra desligar ventilador [s; -1=Off]",
      "max": 9999,
      "min": -1,
      "t": "i16",
      "u": 22,
      "w": 1
    },
    {
      "a": 52,
      "cat": 10,
      "fc": 3,
      "g": 15,
      "id": 53,
      "k": "F52",
      "l": "[vfan_ctrl_t] Temperatura controle do ventilador variavel",
      "max": 1050,
      "min": -500,
      "s": 0.1,
      "t": "i16",
      "u": 1,
      "w": 1
    },
    {
      "a": 53,
      "cat": 10,
      "fc": 3,
      "g": 15,
      "id": 54,
      "k": "F53",
      "l": "[vfan_diff] Diferencial controle vent variavel (histerese)",
      "max": 990,
      "min": 10,
      "s": 0.1,
      "t": "i16",
      "u": 1,
      "w": 1
    },
    {
      "a": 54,
      "cat": 10,
      "fc": 3,
      "g": 15,
      "id": 55,
      "k": "F54",
      "l": "[vfan_min_speed] Minima velocidade vent variavel [%]",
      "max": 100,
      "min": 0,
      "t": "u16",
      "u": 3,
      "w": 1
    },
    {
      "a": 55,
      "cat": 10,
      "fc": 3,
      "g": 15,
      "id": 56,
      "k": "F55",
      "l": "[vfan_max_speed] Maxima velocidade vent variavel [%]",
      "max": 100,
      "min": 0,
      "t": "u16",
      "u": 3,
      "w": 1
    },
    {
      "a": 56,
      "cat": 10,
      "fc": 3,
      "g": 15,
      "id": 57,
      "k": "F56",
      "l": "[vfan_off_speed] Velocidade vent variavel c/ compressor desligado [%; 0=Off]",
      "max": 100,
      "min": 0,
      "t": "u16",
      "u": 3,
      "w": 1
    },
    {
      "a": 57,
      "cat": 10,
      "fc": 3,
      "g": 15,
      "id": 58,
      "k": "F57",
      "l": "[vfan_start_s] Tempo partida em velocidade maxima [s; 0=Off]",
      "max": 999,
      "min": 0,
      "t": "u16",
      "u": 22,
      "w": 1
    },
    {
      "a": 58,
      "cat": 10,
      "fc": 3,
      "g": 15,
      "id": 59,
      "k": "F58",
      "l": "[vfan_antifz_lp] Tempo vent variavel min pra ativar antifreeze [min; 0=Off]",
      "max": 999,
      "min": 0,
      "t": "u16",
      "u": 23,
      "w": 1
    },
    {
      "a": 59,
      "cat": 10,
      "fc": 3,
      "g": 15,
      "id": 60,
      "k": "F59",
      "l": "[vfan_antifz_hp] Tempo vent variavel max durante antifreeze [s]",
      "max": 999,
      "min": 10,
      "t": "u16",
      "u": 22,
      "w": 1
    },
    {
      "a": 60,
      "cat": 10,
      "fc": 3,
      "g": 15,
      "id": 61,
      "k": "F60",
      "l": "[din1_mode] Modo funcionamento entrada digital 1 / sensor S3",
      "max": 24,
      "min": 0,
      "t": "u16",
      "w": 1
    },
    {
      "a": 61,
      "cat": 10,
      "fc": 3,
      "g": 15,
      "id": 62,
      "k": "F61",
      "l": "[din2_mode] Modo funcionamento entrada digital 2 / sensor S4",
      "max": 21,
      "min": 0,
      "t": "u16",
      "w": 1
    },
    {
      "a": 62,
      "cat": 10,
      "fc": 3,
      "g": 15,
      "id": 63,
      "k": "F62",
      "l": "[door_defr_time] Tempo porta aberta pra degelo instantaneo [min; 0=Off]",
      "max": 999,
      "min": 0,
      "t": "u16",
      "u": 23,
      "w": 1
    },
    {
      "a": 63,
      "cat": 10,
      "fc": 3,
      "g": 15,
      "id": 64,
      "k": "F63",
      "l": "[door_off_time] Tempo porta aberta pra desligar comp+vent [min; 0=Off]",
      "max": 999,
      "min": 0,
      "t": "u16",
      "u": 23,
      "w": 1
    },
    {
      "a": 64,
      "cat": 10,
      "fc": 3,
      "g": 15,
      "id": 65,
      "k": "F64",
      "l": "[door_lamp_time] Tempo porta fechada pra desligar lampada [min; 0=Off]",
      "max": 999,
      "min": 0,
      "t": "u16",
      "u": 23,
      "w": 1
    },
    {
      "a": 65,
      "cat": 10,
      "fc": 3,
      "g": 15,
      "id": 66,
      "k": "F65",
      "l": "[door_eco_time] Tempo porta fechada pra ativar modo economico [min; 0=Off]",
      "max": 999,
      "min": 0,
      "t": "u16",
      "u": 23,
      "w": 1
    },
    {
      "a": 66,
      "cat": 10,
      "fc": 3,
      "g": 15,
      "id": 67,
      "k": "F66",
      "l": "[comp_type] Tipo de compressor",
      "max": 3,
      "min": 1,
      "t": "u16",
      "w": 1
    },
    {
      "a": 67,
      "cat": 10,
      "fc": 3,
      "g": 15,
      "id": 68,
      "k": "F67",
      "l": "[comp_min_on_s] Tempo minimo compressor ligado [s; 0=Off]",
      "max": 9999,
      "min": 0,
      "t": "u16",
      "u": 22,
      "w": 1
    },
    {
      "a": 68,
      "cat": 10,
      "fc": 3,
      "g": 15,
      "id": 69,
      "k": "F68",
      "l": "[comp_min_off_s] Tempo minimo compressor desligado [s; 0=Off]",
      "max": 9999,
      "min": 0,
      "t": "u16",
      "u": 22,
      "w": 1
    },
    {
      "a": 69,
      "cat": 10,
      "fc": 3,
      "g": 15,
      "id": 70,
      "k": "F69",
      "l": "[comp_on_s1err] Tempo comp ligado c/ erro S1 [min; 0=Off]",
      "max": 999,
      "min": 0,
      "t": "u16",
      "u": 23,
      "w": 1
    },
    {
      "a": 70,
      "cat": 10,
      "fc": 3,
      "g": 15,
      "id": 71,
      "k": "F70",
      "l": "[comp_off_s1err] Tempo comp desligado c/ erro S1 [min; 0=Off]",
      "max": 999,
      "min": 0,
      "t": "u16",
      "u": 23,
      "w": 1
    },
    {
      "a": 71,
      "cat": 10,
      "fc": 3,
      "g": 15,
      "id": 72,
      "k": "F71",
      "l": "[gain_p] Ganho Proporcional (P)",
      "max": 1000,
      "min": 10,
      "s": 0.1,
      "t": "u16",
      "w": 1
    },
    {
      "a": 72,
      "cat": 10,
      "fc": 3,
      "g": 15,
      "id": 73,
      "k": "F72",
      "l": "[time_i] Tempo de Integral (I) [s]",
      "max": 500,
      "min": 1,
      "t": "u16",
      "u": 22,
      "w": 1
    },
    {
      "a": 73,
      "cat": 10,
      "fc": 3,
      "g": 15,
      "id": 74,
      "k": "F73",
      "l": "[time_d] Tempo Derivativo (D) [s; 0=Off]",
      "max": 500,
      "min": 0,
      "t": "u16",
      "u": 22,
      "w": 1
    },
    {
      "a": 74,
      "cat": 10,
      "fc": 3,
      "g": 15,
      "id": 75,
      "k": "F74",
      "l": "[vcomp_pid_min] Freq minima PID compressor variavel [Hz]",
      "max": 300,
      "min": 30,
      "t": "u16",
      "u": 15,
      "w": 1
    },
    {
      "a": 75,
      "cat": 10,
      "fc": 3,
      "g": 15,
      "id": 76,
      "k": "F75",
      "l": "[vcomp_pid_max] Freq maxima PID compressor variavel [Hz]",
      "max": 300,
      "min": 30,
      "t": "u16",
      "u": 15,
      "w": 1
    },
    {
      "a": 76,
      "cat": 10,
      "fc": 3,
      "g": 15,
      "id": 77,
      "k": "F76",
      "l": "[vcomp_max] Freq maxima operacao compressor variavel [Hz/%]",
      "max": 300,
      "min": 30,
      "t": "u16",
      "u": 15,
      "w": 1
    },
    {
      "a": 77,
      "cat": 10,
      "fc": 3,
      "g": 15,
      "id": 78,
      "k": "F77",
      "l": "[vcomp_stop] Freq parada compressor variavel (switch-off) [Hz]",
      "max": 50,
      "min": 0,
      "t": "u16",
      "u": 15,
      "w": 1
    },
    {
      "a": 78,
      "cat": 10,
      "fc": 3,
      "g": 15,
      "id": 79,
      "k": "F78",
      "l": "[vcomp_defr] Freq compressor durante degelo gas quente [Hz/%]",
      "max": 300,
      "min": 30,
      "t": "u16",
      "u": 15,
      "w": 1
    },
    {
      "a": 79,
      "cat": 10,
      "fc": 3,
      "g": 15,
      "id": 80,
      "k": "F79",
      "l": "[vcomp_s1err] Freq compressor c/ erro S1 [Hz/%]",
      "max": 300,
      "min": 30,
      "t": "u16",
      "u": 15,
      "w": 1
    },
    {
      "a": 80,
      "cat": 10,
      "fc": 3,
      "g": 15,
      "id": 81,
      "k": "F80",
      "l": "[vcomp_softstart] Freq partida suave compressor variavel [Hz/%]",
      "max": 300,
      "min": 30,
      "t": "u16",
      "u": 15,
      "w": 1
    },
    {
      "a": 81,
      "cat": 10,
      "fc": 3,
      "g": 15,
      "id": 82,
      "k": "F81",
      "l": "[vcomp_softst_s] Tempo partida suave compressor variavel [s]",
      "max": 999,
      "min": 1,
      "t": "u16",
      "u": 22,
      "w": 1
    },
    {
      "a": 82,
      "cat": 10,
      "fc": 3,
      "g": 15,
      "id": 83,
      "k": "F82",
      "l": "[vcomp_after_sp] Tempo comp variavel ligado apos setpoint [min; 0=Off,999=On]",
      "max": 999,
      "min": 0,
      "t": "u16",
      "u": 23,
      "w": 1
    },
    {
      "a": 83,
      "cat": 10,
      "fc": 3,
      "g": 15,
      "id": 84,
      "k": "F83",
      "l": "[vcomp_lube_lp] Tempo comp abaixo F85 pra lubrificacao [min; 10=Off]",
      "max": 1440,
      "min": 10,
      "t": "u16",
      "u": 23,
      "w": 1
    },
    {
      "a": 84,
      "cat": 10,
      "fc": 3,
      "g": 15,
      "id": 85,
      "k": "F84",
      "l": "[vcomp_lube_hp] Tempo comp em F76 pra lubrificacao [s]",
      "max": 999,
      "min": 10,
      "t": "u16",
      "u": 22,
      "w": 1
    },
    {
      "a": 85,
      "cat": 10,
      "fc": 3,
      "g": 15,
      "id": 86,
      "k": "F85",
      "l": "[vcomp_lube_min] Freq minima controle lubrificacao [Hz/%]",
      "max": 300,
      "min": 30,
      "t": "u16",
      "u": 15,
      "w": 1
    },
    {
      "a": 86,
      "cat": 10,
      "fc": 3,
      "g": 15,
      "id": 87,
      "k": "F86",
      "l": "[vcomp_max_time] Tempo max comp variavel na freq maxima [min; 0=Off]",
      "max": 9999,
      "min": 0,
      "t": "u16",
      "u": 23,
      "w": 1
    },
    {
      "a": 87,
      "cat": 4,
      "fc": 3,
      "g": 15,
      "id": 88,
      "k": "F87",
      "l": "[alarm_low] Limite temp baixa (diferencial ao setpoint) [10=Off]",
      "max": 999,
      "min": 10,
      "s": 0.1,
      "t": "i16",
      "u": 1,
      "w": 1
    },
    {
      "a": 88,
      "cat": 4,
      "fc": 3,
      "g": 15,
      "id": 89,
      "k": "F88",
      "l": "[alarm_high] Limite temp alta (diferencial ao setpoint) [10=Off]",
      "max": 999,
      "min": 10,
      "s": 0.1,
      "t": "i16",
      "u": 1,
      "w": 1
    },
    {
      "a": 89,
      "cat": 10,
      "fc": 3,
      "g": 15,
      "id": 90,
      "k": "F89",
      "l": "[aux_mode] Modo da saida AUX",
      "max": 7,
      "min": 0,
      "t": "u16",
      "w": 1
    },
    {
      "a": 90,
      "cat": 10,
      "fc": 3,
      "g": 15,
      "id": 91,
      "k": "F90",
      "l": "[aux_on_wd] Horario ligar AUX se F89=5 (Seg-Sex)",
      "max": 1439,
      "min": 0,
      "t": "u16",
      "u": 23,
      "w": 1
    },
    {
      "a": 91,
      "cat": 10,
      "fc": 3,
      "g": 15,
      "id": 92,
      "k": "F91",
      "l": "[aux_off_wd] Horario desligar AUX se F89=5 (Seg-Sex; 1440=Off)",
      "max": 1440,
      "min": 0,
      "t": "u16",
      "u": 23,
      "w": 1
    },
    {
      "a": 92,
      "cat": 10,
      "fc": 3,
      "g": 15,
      "id": 93,
      "k": "F92",
      "l": "[aux_on_sat] Horario ligar AUX se F89=5 (Sabado)",
      "max": 1439,
      "min": 0,
      "t": "u16",
      "u": 23,
      "w": 1
    },
    {
      "a": 93,
      "cat": 10,
      "fc": 3,
      "g": 15,
      "id": 94,
      "k": "F93",
      "l": "[aux_off_sat] Horario desligar AUX se F89=5 (Sabado)",
      "max": 1440,
      "min": 0,
      "t": "u16",
      "u": 23,
      "w": 1
    },
    {
      "a": 94,
      "cat": 10,
      "fc": 3,
      "g": 15,
      "id": 95,
      "k": "F94",
      "l": "[aux_on_sun] Horario ligar AUX se F89=5 (Domingo)",
      "max": 1439,
      "min": 0,
      "t": "u16",
      "u": 23,
      "w": 1
    },
    {
      "a": 95,
      "cat": 10,
      "fc": 3,
      "g": 15,
      "id": 96,
      "k": "F95",
      "l": "[aux_off_sun] Horario desligar AUX se F89=5 (Domingo)",
      "max": 1440,
      "min": 0,
      "t": "u16",
      "u": 23,
      "w": 1
    },
    {
      "a": 96,
      "cat": 10,
      "fc": 3,
      "g": 15,
      "id": 97,
      "k": "F96",
      "l": "[alarm_mode_s1] Modo alarmes temp ambiente S1 (0=relativo, 1=absoluto)",
      "max": 1,
      "min": 0,
      "t": "u16",
      "w": 1
    },
    {
      "a": 97,
      "cat": 4,
      "fc": 3,
      "g": 15,
      "id": 98,
      "k": "F97",
      "l": "[alarm_low_amb] Alarme temp ambiente baixa (S1)",
      "max": 1050,
      "min": -500,
      "s": 0.1,
      "t": "i16",
      "u": 1,
      "w": 1
    },
    {
      "a": 98,
      "cat": 4,
      "fc": 3,
      "g": 15,
      "id": 99,
      "k": "F98",
      "l": "[alarm_high_amb] Alarme temp ambiente alta (S1)",
      "max": 1050,
      "min": -500,
      "s": 0.1,
      "t": "i16",
      "u": 1,
      "w": 1
    },
    {
      "a": 99,
      "cat": 10,
      "fc": 3,
      "g": 15,
      "id": 100,
      "k": "F99",
      "l": "[door_alarm_time] Tempo porta aberta pra alarme sonoro [min; 0=Off]",
      "max": 999,
      "min": 0,
      "t": "u16",
      "u": 23,
      "w": 1
    },
    {
      "a": 100,
      "cat": 10,
      "fc": 3,
      "g": 15,
      "id": 101,
      "k": "F100",
      "l": "[alarm_valid_t] Tempo validacao alarme por temperatura [min; 0=Off]",
      "max": 999,
      "min": 0,
      "t": "u16",
      "u": 23,
      "w": 1
    },
    {
      "a": 101,
      "cat": 10,
      "fc": 3,
      "g": 15,
      "id": 102,
      "k": "F101",
      "l": "[alarm_inh_boot] Tempo inibicao alarme na energizacao [min; 0=Off]",
      "max": 999,
      "min": 0,
      "t": "u16",
      "u": 23,
      "w": 1
    },
    {
      "a": 102,
      "cat": 4,
      "fc": 3,
      "g": 15,
      "id": 103,
      "k": "F102",
      "l": "[comp_max_no_sp] Tempo max comp ligado sem atingir setpoint [h; 0=Off]",
      "max": 999,
      "min": 0,
      "t": "u16",
      "u": 24,
      "w": 1
    },
    {
      "a": 103,
      "cat": 10,
      "fc": 3,
      "g": 15,
      "id": 104,
      "k": "F103",
      "l": "[comp_maint_h] Tempo max operacao comp pra alarme manutencao (horimetro) [h; 0=Off]",
      "max": 9999,
      "min": 0,
      "t": "u16",
      "u": 24,
      "w": 1
    },
    {
      "a": 104,
      "cat": 10,
      "fc": 3,
      "g": 15,
      "id": 105,
      "k": "F104",
      "l": "[defr_end_signal] Indicacao alarme degelo finalizado por tempo",
      "max": 1,
      "min": 0,
      "t": "u16",
      "w": 1
    },
    {
      "a": 105,
      "cat": 2,
      "fc": 3,
      "g": 15,
      "id": 106,
      "k": "F105",
      "l": "[anticond_setp] Setpoint anti-condensacao (aquecimento sensor S3)",
      "max": 1050,
      "min": -500,
      "s": 0.1,
      "t": "i16",
      "u": 1,
      "w": 1
    },
    {
      "a": 106,
      "cat": 10,
      "fc": 3,
      "g": 15,
      "id": 107,
      "k": "F106",
      "l": "[anticond_diff] Diferencial anti-condensacao (S3)",
      "max": 200,
      "min": 1,
      "s": 0.1,
      "t": "i16",
      "u": 1,
      "w": 1
    },
    {
      "a": 107,
      "cat": 10,
      "fc": 3,
      "g": 15,
      "id": 108,
      "k": "F107",
      "l": "[buzzer_enable] Habilita alarme sonoro (buzzer)",
      "max": 1,
      "min": 0,
      "t": "u16",
      "w": 1
    },
    {
      "a": 108,
      "cat": 10,
      "fc": 3,
      "g": 15,
      "id": 109,
      "k": "F108",
      "l": "[gasket_ctrl] Habilita controle aquecimento de gaxetas",
      "max": 2,
      "min": 0,
      "t": "u16",
      "w": 1
    },
    {
      "a": 109,
      "cat": 10,
      "fc": 3,
      "g": 15,
      "id": 110,
      "k": "F109",
      "l": "[gasket_t] Limite temperatura ativacao gaxetas",
      "max": 1050,
      "min": -500,
      "s": 0.1,
      "t": "i16",
      "u": 1,
      "w": 1
    },
    {
      "a": 110,
      "cat": 10,
      "fc": 3,
      "g": 15,
      "id": 111,
      "k": "F110",
      "l": "[gasket_diff] Diferencial controle gaxetas",
      "max": 200,
      "min": 1,
      "s": 0.1,
      "t": "i16",
      "u": 1,
      "w": 1
    },
    {
      "a": 111,
      "cat": 10,
      "fc": 3,
      "g": 15,
      "id": 112,
      "k": "F111",
      "l": "[gasket_on_min] Tempo saida ligada no controle de gaxetas [min]",
      "max": 9999,
      "min": 1,
      "t": "u16",
      "u": 23,
      "w": 1
    },
    {
      "a": 112,
      "cat": 10,
      "fc": 3,
      "g": 15,
      "id": 113,
      "k": "F112",
      "l": "[gasket_off_min] Tempo saida desligada no controle de gaxetas [min; 0=Off]",
      "max": 9999,
      "min": 0,
      "t": "u16",
      "u": 23,
      "w": 1
    },
    {
      "a": 113,
      "cat": 4,
      "fc": 3,
      "g": 15,
      "id": 114,
      "k": "F113",
      "l": "[alarm_high_cond] Alarme temp alta condensador S3 (visual/sonoro; 0=Off em C)",
      "max": 1050,
      "min": 0,
      "s": 0.1,
      "t": "i16",
      "u": 1,
      "w": 1
    },
    {
      "a": 114,
      "cat": 4,
      "fc": 3,
      "g": 15,
      "id": 115,
      "k": "F114",
      "l": "[cond_off_t] Temp max condensador S3 pra desligar saidas (0=Off em C)",
      "max": 1050,
      "min": 0,
      "s": 0.1,
      "t": "i16",
      "u": 1,
      "w": 1
    },
    {
      "a": 115,
      "cat": 10,
      "fc": 3,
      "g": 15,
      "id": 116,
      "k": "F115",
      "l": "[cond_off_diff] Diferencial temp max condensador (histerese)",
      "max": 200,
      "min": 1,
      "s": 0.1,
      "t": "i16",
      "u": 1,
      "w": 1
    },
    {
      "a": 116,
      "cat": 10,
      "fc": 3,
      "g": 15,
      "id": 117,
      "k": "F116",
      "l": "[hp_confirm_s] Tempo confirmar alarme alta pressao [s]",
      "max": 60,
      "min": 0,
      "t": "u16",
      "u": 22,
      "w": 1
    },
    {
      "a": 117,
      "cat": 10,
      "fc": 3,
      "g": 15,
      "id": 118,
      "k": "F117",
      "l": "[lp_confirm_s] Tempo confirmar alarme baixa pressao [s]",
      "max": 180,
      "min": 0,
      "t": "u16",
      "u": 22,
      "w": 1
    },
    {
      "a": 118,
      "cat": 10,
      "fc": 3,
      "g": 15,
      "id": 119,
      "k": "F118",
      "l": "[lp_init_delay] Tempo retardo inicial pra monitorar baixa pressao [s]",
      "max": 600,
      "min": 30,
      "t": "u16",
      "u": 22,
      "w": 1
    },
    {
      "a": 119,
      "cat": 10,
      "fc": 3,
      "g": 15,
      "id": 120,
      "k": "F119",
      "l": "[hp_retry_min] Tempo retardo pos-alarme alta pressao [min]",
      "max": 10,
      "min": 1,
      "t": "u16",
      "u": 23,
      "w": 1
    },
    {
      "a": 120,
      "cat": 10,
      "fc": 3,
      "g": 15,
      "id": 121,
      "k": "F120",
      "l": "[lp_retry_min] Tempo retardo pos-alarme baixa pressao [min]",
      "max": 10,
      "min": 1,
      "t": "u16",
      "u": 23,
      "w": 1
    },
    {
      "a": 121,
      "cat": 10,
      "fc": 3,
      "g": 15,
      "id": 122,
      "k": "F121",
      "l": "[volt_min] Tensao minima alimentacao (protecao) [V]",
      "max": 400,
      "min": 100,
      "s": 0.1,
      "t": "u16",
      "u": 4,
      "w": 1
    },
    {
      "a": 122,
      "cat": 10,
      "fc": 3,
      "g": 15,
      "id": 123,
      "k": "F122",
      "l": "[volt_max] Tensao maxima alimentacao (protecao) [V]",
      "max": 400,
      "min": 100,
      "s": 0.1,
      "t": "u16",
      "u": 4,
      "w": 1
    },
    {
      "a": 123,
      "cat": 10,
      "fc": 3,
      "g": 15,
      "id": 124,
      "k": "F123",
      "l": "[volt_offset] Offset indicacao de tensao [V]",
      "max": 100,
      "min": -100,
      "s": 0.1,
      "t": "i16",
      "u": 4,
      "w": 1
    },
    {
      "a": 124,
      "cat": 10,
      "fc": 3,
      "g": 15,
      "id": 125,
      "k": "F124",
      "l": "[volt_valid_s] Tempo validacao tensao [s]",
      "max": 30,
      "min": 1,
      "t": "u16",
      "u": 22,
      "w": 1
    },
    {
      "a": 125,
      "cat": 10,
      "fc": 3,
      "g": 15,
      "id": 126,
      "k": "F125",
      "l": "[haccp_enable] Habilita registros dos alarmes HACCP",
      "max": 1,
      "min": 0,
      "t": "u16",
      "w": 1
    },
    {
      "a": 126,
      "cat": 4,
      "fc": 3,
      "g": 15,
      "id": 127,
      "k": "F126",
      "l": "[haccp_alarm_low] HACCP - Alarme temp ambiente baixa",
      "max": 1050,
      "min": -500,
      "s": 0.1,
      "t": "i16",
      "u": 1,
      "w": 1
    },
    {
      "a": 127,
      "cat": 4,
      "fc": 3,
      "g": 15,
      "id": 128,
      "k": "F127",
      "l": "[haccp_alarm_hi] HACCP - Alarme temp ambiente alta",
      "max": 1050,
      "min": -500,
      "s": 0.1,
      "t": "i16",
      "u": 1,
      "w": 1
    },
    {
      "a": 128,
      "cat": 10,
      "fc": 3,
      "g": 15,
      "id": 129,
      "k": "F128",
      "l": "[haccp_inh_min] HACCP - Tempo inibicao alarmes [min; 0=Off]",
      "max": 999,
      "min": 0,
      "t": "u16",
      "u": 23,
      "w": 1
    },
    {
      "a": 129,
      "cat": 10,
      "fc": 3,
      "g": 15,
      "id": 130,
      "k": "F129",
      "l": "[dl_mode] Modo operacao datalogger",
      "max": 2,
      "min": 0,
      "t": "u16",
      "w": 1
    },
    {
      "a": 130,
      "cat": 10,
      "fc": 3,
      "g": 15,
      "id": 131,
      "k": "F130",
      "l": "[dl_sample_s] Periodo amostragem datalogger [s]",
      "max": 999,
      "min": 10,
      "t": "u16",
      "u": 22,
      "w": 1
    },
    {
      "a": 131,
      "cat": 10,
      "fc": 3,
      "g": 15,
      "id": 132,
      "k": "F131",
      "l": "[dl_amb_delta] Variacao min temp ambiente pra forcar escrita datalogger [°C; 0=Off]",
      "max": 100,
      "min": 0,
      "s": 0.1,
      "t": "u16",
      "u": 1,
      "w": 1
    },
    {
      "a": 132,
      "cat": 10,
      "fc": 3,
      "g": 15,
      "id": 133,
      "k": "F132",
      "l": "[dl_io_change] Variacao I/O ou saidas forca escrita dados",
      "max": 1,
      "min": 0,
      "t": "u16",
      "w": 1
    },
    {
      "a": 133,
      "cat": 10,
      "fc": 3,
      "g": 15,
      "id": 134,
      "k": "F133",
      "l": "[dl_overwrite] Sobrescrever registros antigos qdo memoria cheia",
      "max": 1,
      "min": 0,
      "t": "u16",
      "w": 1
    },
    {
      "a": 134,
      "cat": 10,
      "fc": 3,
      "g": 15,
      "id": 135,
      "k": "F134",
      "l": "[filter_mode] Modo atuacao filtro digital",
      "max": 1,
      "min": 0,
      "t": "u16",
      "w": 1
    },
    {
      "a": 135,
      "cat": 10,
      "fc": 3,
      "g": 15,
      "id": 136,
      "k": "F135",
      "l": "[filter_s1_up] Intensidade filtro digital S1 (subida) [s; 0=Off]",
      "max": 20,
      "min": 0,
      "t": "u16",
      "u": 22,
      "w": 1
    },
    {
      "a": 136,
      "cat": 10,
      "fc": 3,
      "g": 15,
      "id": 137,
      "k": "F136",
      "l": "[filter_s1_dn] Intensidade filtro digital S1 (descida) [s; 0=Off]",
      "max": 20,
      "min": 0,
      "t": "u16",
      "u": 22,
      "w": 1
    },
    {
      "a": 137,
      "cat": 10,
      "fc": 3,
      "g": 15,
      "id": 138,
      "k": "F137",
      "l": "[offset_s1] Deslocamento indicacao sensor S1",
      "max": 200,
      "min": -200,
      "s": 0.1,
      "t": "i16",
      "u": 1,
      "w": 1
    },
    {
      "a": 138,
      "cat": 10,
      "fc": 3,
      "g": 15,
      "id": 139,
      "k": "F138",
      "l": "[offset_s2] Deslocamento indicacao sensor S2 (-201=Off)",
      "max": 200,
      "min": -200,
      "s": 0.1,
      "t": "i16",
      "u": 1,
      "w": 1
    },
    {
      "a": 139,
      "cat": 10,
      "fc": 3,
      "g": 15,
      "id": 140,
      "k": "F139",
      "l": "[offset_s3] Deslocamento indicacao sensor S3",
      "max": 200,
      "min": -200,
      "s": 0.1,
      "t": "i16",
      "u": 1,
      "w": 1
    },
    {
      "a": 140,
      "cat": 10,
      "fc": 3,
      "g": 15,
      "id": 141,
      "k": "F140",
      "l": "[offset_s4] Deslocamento indicacao sensor S4",
      "max": 200,
      "min": -200,
      "s": 0.1,
      "t": "i16",
      "u": 1,
      "w": 1
    },
    {
      "a": 141,
      "cat": 10,
      "fc": 3,
      "g": 15,
      "id": 142,
      "k": "F141",
      "l": "[disp_pref] Indicacao preferencial no display",
      "max": 5,
      "min": 1,
      "t": "u16",
      "w": 1
    },
    {
      "a": 142,
      "cat": 10,
      "fc": 3,
      "g": 15,
      "id": 143,
      "k": "F142",
      "l": "[disp_lock_defr] Indicacao S1 travada durante degelo",
      "max": 2,
      "min": 0,
      "t": "u16",
      "w": 1
    },
    {
      "a": 143,
      "cat": 10,
      "fc": 3,
      "g": 15,
      "id": 144,
      "k": "F143",
      "l": "[disp_lock_max] Tempo max indicacao travada no degelo [min; 0=Off]",
      "max": 999,
      "min": 0,
      "t": "u16",
      "u": 23,
      "w": 1
    },
    {
      "a": 144,
      "cat": 10,
      "fc": 3,
      "g": 15,
      "id": 145,
      "k": "F144",
      "l": "[func_lock_mode] Modo bloqueio de funcoes",
      "max": 2,
      "min": 0,
      "t": "u16",
      "w": 1
    },
    {
      "a": 145,
      "cat": 10,
      "fc": 3,
      "g": 15,
      "id": 146,
      "k": "F145",
      "l": "[func_lock_time] Tempo para bloqueio de funcoes [s]",
      "max": 60,
      "min": 15,
      "t": "u16",
      "u": 22,
      "w": 1
    },
    {
      "a": 146,
      "cat": 10,
      "fc": 3,
      "g": 15,
      "id": 147,
      "k": "F146",
      "l": "[ctrl_off] Desligamento das funcoes de controle",
      "max": 2,
      "min": 0,
      "t": "u16",
      "w": 1
    },
    {
      "a": 147,
      "cat": 10,
      "fc": 3,
      "g": 15,
      "id": 148,
      "k": "F147",
      "l": "[rs485_addr] Endereco do instrumento na rede RS-485 (RO)",
      "t": "u16"
    },
    {
      "a": 148,
      "cat": 10,
      "fc": 3,
      "g": 15,
      "id": 149,
      "k": "F148",
      "l": "[temp_unit] Unidade temperatura (0=°C, 1=°F) — SO aceita write via FC06",
      "max": 1,
      "min": 0,
      "t": "u16",
      "w": 1
    },
    {
      "a": 149,
      "cat": 10,
      "fc": 3,
      "g": 15,
      "id": 150,
      "k": "F149",
      "l": "[sensor_beta] Tipo sensor (0=Beta FG, 1=Beta 3435)",
      "max": 1,
      "min": 0,
      "t": "u16",
      "w": 1
    },
    {
      "a": 150,
      "cat": 10,
      "fc": 3,
      "g": 15,
      "id": 151,
      "k": "F150",
      "l": "[mb_addr] Endereco Modbus (RO)",
      "t": "u16"
    },
    {
      "a": 151,
      "cat": 10,
      "fc": 3,
      "g": 15,
      "id": 152,
      "k": "F151",
      "l": "[mb_baud] Baud rate Modbus (RO; 0..6 -> 1200..57600)",
      "t": "u16"
    },
    {
      "a": 152,
      "cat": 10,
      "fc": 3,
      "g": 15,
      "id": 153,
      "k": "F152",
      "l": "[mb_parity] Paridade Modbus (RO; 0=N,1=E,2=O)",
      "t": "u16"
    },
    {
      "a": 153,
      "cat": 10,
      "fc": 3,
      "g": 15,
      "id": 154,
      "k": "F153",
      "l": "[mb_stop] Stop bits Modbus (RO; 0=1,1=2)",
      "t": "u16"
    },
    {
      "a": 154,
      "cat": 10,
      "fc": 3,
      "g": 15,
      "id": 155,
      "k": "F154",
      "l": "[proto_mode] Modo protocolo Serial (RO; 0=Sitrad, 1=Modbus)",
      "t": "u16"
    },
    {
      "a": 160,
      "cat": 8,
      "fc": 3,
      "g": 15,
      "id": 156,
      "k": "A0",
      "l": "[rtc_dia] RTC: Dia do mes",
      "max": 31,
      "min": 1,
      "t": "u16",
      "w": 1
    },
    {
      "a": 161,
      "cat": 8,
      "fc": 3,
      "g": 15,
      "id": 157,
      "k": "A1",
      "l": "[rtc_mes] RTC: Mes",
      "max": 12,
      "min": 1,
      "t": "u16",
      "w": 1
    },
    {
      "a": 162,
      "cat": 8,
      "fc": 3,
      "g": 15,
      "id": 158,
      "k": "A2",
      "l": "[rtc_ano] RTC: Ano (2 digitos)",
      "max": 99,
      "min": 0,
      "t": "u16",
      "w": 1
    },
    {
      "a": 163,
      "cat": 8,
      "fc": 3,
      "g": 15,
      "id": 159,
      "k": "A3",
      "l": "[rtc_hora] RTC: Horas",
      "max": 23,
      "min": 0,
      "t": "u16",
      "w": 1
    },
    {
      "a": 164,
      "cat": 8,
      "fc": 3,
      "g": 15,
      "id": 160,
      "k": "A4",
      "l": "[rtc_min] RTC: Minutos",
      "max": 59,
      "min": 0,
      "t": "u16",
      "w": 1
    },
    {
      "a": 165,
      "cat": 6,
      "fc": 3,
      "g": 4,
      "id": 161,
      "k": "A5",
      "l": "[vcomp_freq] Frequencia/Tensao compressor variavel [Hz ou %]",
      "t": "u16",
      "u": 15
    },
    {
      "a": 166,
      "cat": 6,
      "fc": 3,
      "g": 4,
      "id": 162,
      "k": "A6",
      "l": "[vfan_v] Tensao ventilador variavel [%]",
      "t": "u16",
      "u": 3
    },
    {
      "a": 167,
      "cat": 1,
      "fc": 3,
      "g": 4,
      "id": 163,
      "k": "A7",
      "l": "[s1_temp] Temperatura sensor S1 (ambiente)",
      "s": 0.1,
      "t": "i16",
      "u": 1
    },
    {
      "a": 168,
      "cat": 1,
      "fc": 3,
      "g": 4,
      "id": 164,
      "k": "A8",
      "l": "[s2_temp] Temperatura sensor S2 (evaporador)",
      "s": 0.1,
      "t": "i16",
      "u": 1
    },
    {
      "a": 169,
      "cat": 1,
      "fc": 3,
      "g": 4,
      "id": 165,
      "k": "A9",
      "l": "[s3_temp] Temperatura sensor S3 (auxiliar/condensador)",
      "s": 0.1,
      "t": "i16",
      "u": 1
    },
    {
      "a": 170,
      "cat": 1,
      "fc": 3,
      "g": 4,
      "id": 166,
      "k": "AA",
      "l": "[s4_temp] Temperatura sensor S4 (auxiliar)",
      "s": 0.1,
      "t": "i16",
      "u": 1
    },
    {
      "a": 171,
      "cat": 6,
      "fc": 3,
      "g": 7,
      "id": 167,
      "k": "AB",
      "l": "[sup_volt] Tensao alimentacao (controlador 12/24V) [V]",
      "s": 0.1,
      "t": "u16",
      "u": 4
    },
    {
      "a": 172,
      "bm": "sw1",
      "cat": 5,
      "fc": 3,
      "g": 4,
      "id": 168,
      "k": "AC",
      "l": "[sw1] Status Word 1: Saidas, entradas digitais, processos",
      "t": "u16"
    },
    {
      "a": 173,
      "bm": "sw2",
      "cat": 5,
      "fc": 3,
      "g": 4,
      "id": 169,
      "k": "AD",
      "l": "[sw2] Status Word 2: Erros e sinalizacoes",
      "t": "u16"
    },
    {
      "a": 174,
      "bm": "sw3",
      "cat": 5,
      "fc": 3,
      "g": 4,
      "id": 170,
      "k": "AE",
      "l": "[sw3] Status Word 3: Alarmes",
      "t": "u16"
    },
    {
      "a": 175,
      "cat": 10,
      "fc": 3,
      "g": 7,
      "id": 171,
      "k": "AF",
      "l": "[proc_time] Tempo processo atual [min]",
      "t": "u16",
      "u": 23
    },
    {
      "a": 176,
      "cat": 10,
      "fc": 3,
      "g": 7,
      "id": 172,
      "k": "B0",
      "l": "[horim] Tempo horimetro compressor [h]",
      "t": "u16",
      "u": 24
    },
    {
      "a": 177,
      "cat": 10,
      "fc": 3,
      "g": 15,
      "id": 173,
      "k": "B1",
      "l": "[vendor_id] ID do fabricante (0x4647='FG')",
      "t": "u16"
    },
    {
      "a": 178,
      "cat": 10,
      "fc": 3,
      "g": 15,
      "id": 174,
      "k": "B2",
      "l": "[product_id] ID do produto (625 = TC-970E)",
      "t": "u16"
    },
    {
      "a": 179,
      "cat": 10,
      "fc": 3,
      "g": 15,
      "id": 175,
      "k": "B3",
      "l": "[product_ver] Versao do produto (04)",
      "t": "u16"
    },
    {
      "a": 250,
      "cat": 3,
      "fc": 3,
      "g": 15,
      "id": 176,
      "k": "FA",
      "l": "[test_mode_en] Habilita modo teste (obrigatorio pra 0xFB..0x101)",
      "max": 1,
      "min": 0,
      "t": "u16",
      "w": 1
    },
    {
      "a": 251,
      "cat": 3,
      "fc": 3,
      "g": 15,
      "id": 177,
      "k": "FB",
      "l": "[cmd_comp] Liga/Desliga saida COMP (modo teste)",
      "max": 1,
      "min": 0,
      "t": "u16",
      "w": 1
    },
    {
      "a": 252,
      "cat": 3,
      "fc": 3,
      "g": 15,
      "id": 178,
      "k": "FC",
      "l": "[cmd_fan] Liga/Desliga saida FAN (modo teste)",
      "max": 1,
      "min": 0,
      "t": "u16",
      "w": 1
    },
    {
      "a": 253,
      "cat": 3,
      "fc": 3,
      "g": 15,
      "id": 179,
      "k": "FD",
      "l": "[cmd_defr] Liga/Desliga saida DEFR (modo teste)",
      "max": 1,
      "min": 0,
      "t": "u16",
      "w": 1
    },
    {
      "a": 254,
      "cat": 3,
      "fc": 3,
      "g": 15,
      "id": 180,
      "k": "FE",
      "l": "[cmd_aux] Liga/Desliga saida AUX (modo teste)",
      "max": 1,
      "min": 0,
      "t": "u16",
      "w": 1
    },
    {
      "a": 255,
      "cat": 3,
      "fc": 3,
      "g": 15,
      "id": 181,
      "k": "FF",
      "l": "[cmd_vcc_freq] Frequencia saida VCC COMP [Hz] (modo teste; prioridade sobre tensao)",
      "max": 300,
      "min": 0,
      "t": "u16",
      "u": 15,
      "w": 1
    },
    {
      "a": 256,
      "cat": 3,
      "fc": 3,
      "g": 15,
      "id": 182,
      "k": "100",
      "l": "[cmd_vcc_v] Tensao saida VCC COMP [%] (modo teste)",
      "max": 100,
      "min": 0,
      "t": "u16",
      "u": 3,
      "w": 1
    },
    {
      "a": 257,
      "cat": 3,
      "fc": 3,
      "g": 15,
      "id": 183,
      "k": "101",
      "l": "[cmd_vsf_v] Tensao saida VSF FAN [%] (modo teste)",
      "max": 100,
      "min": 0,
      "t": "u16",
      "u": 3,
      "w": 1
    },
    {
      "a": 258,
      "cat": 3,
      "fc": 3,
      "g": 15,
      "id": 184,
      "k": "102",
      "l": "[cmd_lamp] Liga/Desliga lampada",
      "max": 1,
      "min": 0,
      "t": "u16",
      "w": 1
    },
    {
      "a": 259,
      "cat": 3,
      "fc": 3,
      "g": 15,
      "id": 185,
      "k": "103",
      "l": "[cmd_defr_man] Liga/Desliga degelo manual",
      "max": 1,
      "min": 0,
      "t": "u16",
      "w": 1
    },
    {
      "a": 260,
      "cat": 3,
      "fc": 3,
      "g": 15,
      "id": 186,
      "k": "104",
      "l": "[cmd_eco] Liga/Desliga modo economico",
      "max": 1,
      "min": 0,
      "t": "u16",
      "w": 1
    },
    {
      "a": 261,
      "cat": 3,
      "fc": 3,
      "g": 15,
      "id": 187,
      "k": "105",
      "l": "[cmd_ff] Liga/Desliga modo Fast Freezing",
      "max": 1,
      "min": 0,
      "t": "u16",
      "w": 1
    },
    {
      "a": 262,
      "cat": 3,
      "fc": 3,
      "g": 15,
      "id": 188,
      "k": "106",
      "l": "[cmd_ctrl] Liga/Desliga funcoes de controle",
      "max": 1,
      "min": 0,
      "t": "u16",
      "w": 1
    },
    {
      "a": 263,
      "cat": 3,
      "fc": 3,
      "g": 15,
      "id": 189,
      "k": "107",
      "l": "[cmd_lock] Liga/Desliga bloqueio de funcoes",
      "max": 1,
      "min": 0,
      "t": "u16",
      "w": 1
    },
    {
      "a": 264,
      "cat": 9,
      "fc": 3,
      "g": 15,
      "id": 190,
      "k": "108",
      "l": "[reset_horim] Resetar horimetro",
      "max": 1,
      "min": 0,
      "t": "u16",
      "w": 1
    },
    {
      "a": 265,
      "cat": 3,
      "fc": 3,
      "g": 15,
      "id": 191,
      "k": "109",
      "l": "[buzzer_off] Inibir buzzer",
      "max": 1,
      "min": 0,
      "t": "u16",
      "w": 1
    }
  ],
  "schema": 2,
  "vendor": "fullgauge"
}
